<ns0:eml xmlns:ns0="eml://ecoinformatics.org/eml-2.1.1" xmlns:xsi="http://www.w3.org/2001/XMLSchema-instance" packageId="df35c.22.20" system="knb" xsi:schemaLocation="eml://ecoinformatics.org/eml-2.1.1 eml.xsd">  <access authSystem="knb" order="allowFirst"><allow><principal>public</principal>
<permission>read</permission>
</allow>
<allow><principal>cn=evos,o=NCEAS,dc=ecoinformatics,dc=org</principal>
<permission>all</permission>
</allow>
</access>
<dataset> <title>Geographic Extent, Temporal Persistence and Mapping of Floating Oil from the the Exxon Valdez Oil Spill: 1989</title>
 <creator id="1362169133661"><individualName><givenName>Marshal</givenName>
 <surName>Kendziorek</surName>
 </individualName>
 <positionName>PI</positionName>
 <electronicMailAddress>marshalkendziorek@gmail.com</electronicMailAddress>
 </creator>
 <associatedParty id="1370284734203"><individualName><givenName>Emma</givenName>
 <surName>Freeman</surName>
 </individualName>
 <organizationName>National Center for Ecological Analysis and Synthesis</organizationName>
 <positionName>Graduate Student Researcher</positionName>
 <address><deliveryPoint>735 State Street</deliveryPoint>
 <deliveryPoint>Suite 300</deliveryPoint>
 <city>Santa Barbara</city>
 <administrativeArea>California</administrativeArea>
 <postalCode>93101</postalCode>
 <country>USA</country>
 </address>
 <phone phonetype="voice">1.805.892.2500</phone>
 <onlineUrl>http://www.nceas.ucsb.edu</onlineUrl>
 <role>Processor</role>
 </associatedParty>
 <abstract><para>Information about this project comes from the original project proposal submitted in October, 1989. No Final Report is available.

The general mission of this Natural Resource Damage Assessment floating oil mapping effort was to document the extent, amount and persistence of oil resulting from the EXXON VALDEZ oil spill. Maps have been produced on a regular basis showing the location of oil from aerial surveys from the first day of the spill on March 24, 1989. While the aerial overflight mapping effort has been reduced since mid May, to one flight a day from two or three, there are still regular aerial overflights being performed to monitor the location and extent of oil in the water. Another source of information that yielded answers on the extent of floating oil was satellite imagery. The data source used here consists of imagery obtained from a variety of polar-orbiting satellites. The function of the satellite imagery portion of this study is to revise digital filtering techniques to remove noise and to perform digital enhancements to improve the identification of oil. In addition, the satellite imagery will be enhanced to provide oceanographic data useful in determining the oil's trajectory as well as its weathering, mixing with suspended sediments and related evolution. Finally, there is a possibility that some of the satellite imagery will yield information that will document the extent of oiled beaches.

The aerial overflights produce three basic data types. The first type is a hard copy of a nautical chart with observers notes and markings indicating the location and extent of the oil as well as the flight track taken by this crew. The second data type is video tape showing the oil on the water. The third data type is a written report from the observers with any other observations they may have as well as weather information indicating the observing conditions. In many instances still photographs also exist from the flight. All of this information is combined to ensure the accuracy and reliability of the information.

The satellites produce image format data of the earth's surface in a variety of wavelength bands ranging from blue visible light to the thermal infrared Some of these bands are useful for the identification of oil while others are useful for identification of suspended sediment, the thermal regime, and possibly large concentrations of plankton. The oil signature in most cases is only slightly different from that of the ocean, requiring sophisticated digital image enhancement techniques to separate the two. It is possible that the oil signature will be found to change over time as a result of its weathering. Other techniques are used to display the identified oil relative to regions of suspended sediment where the oil may have become sufficiently heavy to have become submerged.</para>
 </abstract>
 <keywordSet><keyword>prince william sound</keyword>
 <keyword>maps</keyword>
 <keyword>surface oil</keyword>
 <keyword>floating oil</keyword>
 <keyword>aerial</keyword>
 <keyword>lingering oil</keyword>
 </keywordSet>
 <keywordSet><keyword>EVOSTC</keyword>
 <keyword>Exxon Valdez Oil Spill Trustee Council</keyword>
 <keyword>Oil Spill</keyword>
 <keyword>Exxon Valdez</keyword>
 <keyword>Alaska</keyword>
 <keyword>Benthic</keyword>
 <keyword>Imagery</keyword>
 <keyword>Oil and Contaminants</keyword>
 <keyword>Shoreline Habitat and Sensitivity</keyword>
 <keywordThesaurus>Gulf Watch Alaska Thesaurus</keywordThesaurus>
 </keywordSet>
 <intellectualRights><para>This material is based upon work funded by the Exxon Valdez Oil Spill
Trustee Council. Any opinions, findings, conclusions, or recommendations
expressed herein are those of the author(s) and do not necessarily reflect
the views or positions of the Trustee Council.

Standard scientific norms for attribution and credit should be followed
when using this data including to the Owners, Exxon Valdez Oil Spill
Trustee Council and other sources of funding. Please let the Owner know
when this data is used.

This data is licensed under CC0. The person who associated a work with
this deed has dedicated the work to the public domain by waiving all of his
or her rights to the work worldwide under copyright law, including all
related and neighboring rights, to the extent allowed by law. You can copy,
modify, distribute and perform the work, even for commercial purposes, all
without asking permission.</para>
 </intellectualRights>
 <contact id="1362169144365"><individualName><givenName>Marshal</givenName>
 <surName>Kendziorek</surName>
 </individualName>
 <electronicMailAddress>marshalkendziorek@gmail.com</electronicMailAddress>
 </contact>
 <project><title>Geographic Extent, Temporal Persistence, and Mapping of Floating Oil from the Exxon Valdez Oil Spill</title>
 <personnel id="1366224660950"><individualName><givenName>Marshal</givenName>
 <surName>Kendziorek</surName>
 </individualName>
 <role>PI</role>
 </personnel>
 <funding><para>Exxon Valdez Oil Spill Trustee Council Project Number AW01</para>
 </funding>
 </project>
 <otherEntity><entityName>Alaska Peninsula Shoreline Oiling Map</entityName>
 <physical><objectName>EVOS AK Pen shoreline oiling.pdf</objectName>
 <size unit="byte">21073890</size>
 <dataFormat><externallyDefinedFormat><formatName>application/pdf</formatName>
 </externallyDefinedFormat>
 </dataFormat>
 <distribution id="1366225106825"><online><url function="download">ecogrid://knb/df35c.29.1</url>
 </online>
 </distribution>
 </physical>
 <entityType>Other</entityType>
 </otherEntity>
 <otherEntity><entityName>Kenai Peninsula Shoreline Oiling Map</entityName>
 <physical><objectName>EVOS Kenai Pen shoreline oiling.pdf</objectName>
 <size unit="byte">34726184</size>
 <dataFormat><externallyDefinedFormat><formatName>application/pdf</formatName>
 </externallyDefinedFormat>
 </dataFormat>
 <distribution id="1366225168872"><online><url function="download">ecogrid://knb/df35c.30.1</url>
 </online>
 </distribution>
 </physical>
 <entityType>Other</entityType>
 </otherEntity>
 <otherEntity><entityName>Kenai Peninsula Anadromous Fish Streams</entityName>
 <physical><objectName>EVOS KenaiPen anad streams.pdf</objectName>
 <size unit="byte">10482624</size>
 <dataFormat><externallyDefinedFormat><formatName>application/pdf</formatName>
 </externallyDefinedFormat>
 </dataFormat>
 <distribution id="1366225226276"><online><url function="download">ecogrid://knb/df35c.31.1</url>
 </online>
 </distribution>
 </physical>
 <entityType>Other</entityType>
 </otherEntity>
 <otherEntity><entityName>Misc. Oiling Maps</entityName>
 <physical><objectName>EVOS misc.pdf</objectName>
 <size unit="byte">7984630</size>
 <dataFormat><externallyDefinedFormat><formatName>application/pdf</formatName>
 </externallyDefinedFormat>
 </dataFormat>
 <distribution id="1366225301017"><online><url function="download">ecogrid://knb/df35c.32.1</url>
 </online>
 </distribution>
 </physical>
 <entityType>Other</entityType>
 </otherEntity>
 <otherEntity><entityName>Oil on Water 17 April to 1 May 1989</entityName>
 <physical><objectName>EVOS oil on water 17Apr to 1May 1989.pdf</objectName>
 <size unit="byte">35903876</size>
 <dataFormat><externallyDefinedFormat><formatName>application/pdf</formatName>
 </externallyDefinedFormat>
 </dataFormat>
 <distribution id="1366225322760"><online><url function="download">ecogrid://knb/df35c.33.1</url>
 </online>
 </distribution>
 </physical>
 <entityType>Other</entityType>
 </otherEntity>
 <otherEntity><entityName>Oil on Water 27 March to 28 March 1989</entityName>
 <physical><objectName>EVOS oil on water 27Mar to 28Mar 1989.pdf</objectName>
 <size unit="byte">11605260</size>
 <dataFormat><externallyDefinedFormat><formatName>application/pdf</formatName>
 </externallyDefinedFormat>
 </dataFormat>
 <distribution id="1366225340493"><online><url function="download">ecogrid://knb/df35c.34.1</url>
 </online>
 </distribution>
 </physical>
 <entityType>Other</entityType>
 </otherEntity>
 <otherEntity><entityName>Oil on Water 27 March to 3 April 1989</entityName>
 <physical><objectName>EVOS oil on water 27Mar to 3Apr 1989.pdf</objectName>
 <size unit="byte">45930427</size>
 <dataFormat><externallyDefinedFormat><formatName>application/pdf</formatName>
 </externallyDefinedFormat>
 </dataFormat>
 <distribution id="1366225367800"><online><url function="download">ecogrid://knb/df35c.35.1</url>
 </online>
 </distribution>
 </physical>
 <entityType>Other</entityType>
 </otherEntity>
 <otherEntity><entityName>Oil on Water 5 April to 16 April 1989</entityName>
 <physical><objectName>EVOS oil on water 5Apr to 16Apr 1989.pdf</objectName>
 <size unit="byte">42557108</size>
 <dataFormat><externallyDefinedFormat><formatName>application/pdf</formatName>
 </externallyDefinedFormat>
 </dataFormat>
 <distribution id="1366225387983"><online><url function="download">ecogrid://knb/df35c.36.1</url>
 </online>
 </distribution>
 </physical>
 <entityType>Other</entityType>
 </otherEntity>
 <otherEntity><entityName>Composite Overview of Oil Spill Tracking</entityName>
 <physical><objectName>EVOS oil on water Spill620.pdf</objectName>
 <size unit="byte">7626047</size>
 <dataFormat><externallyDefinedFormat><formatName>application/pdf</formatName>
 </externallyDefinedFormat>
 </dataFormat>
 <distribution id="1366225450345"><online><url function="download">ecogrid://knb/df35c.37.1</url>
 </online>
 </distribution>
 </physical>
 <entityType>Other</entityType>
 </otherEntity>
 <otherEntity><entityName>Alaska Shoreline Oiling</entityName>
 <physical><objectName>EVOS PWS shoreline oiling.pdf</objectName>
 <size unit="byte">13559971</size>
 <dataFormat><externallyDefinedFormat><formatName>application/pdf</formatName>
 </externallyDefinedFormat>
 </dataFormat>
 <distribution id="1366225479216"><online><url function="download">ecogrid://knb/df35c.38.1</url>
 </online>
 </distribution>
 </physical>
 <entityType>Other</entityType>
 </otherEntity>
 </dataset>
 </ns0:eml>