<ns0:eml xmlns:ns0="eml://ecoinformatics.org/eml-2.1.1" xmlns:xsi="http://www.w3.org/2001/XMLSchema-instance" packageId="df35b.95.7" system="knb" xsi:schemaLocation="eml://ecoinformatics.org/eml-2.1.1 eml.xsd">  <access authSystem="knb" order="allowFirst"><allow><principal>public</principal>
<permission>read</permission>
</allow>
<allow><principal>cn=evos,o=NCEAS,dc=ecoinformatics,dc=org</principal>
<permission>read</permission>
<permission>write</permission>
<permission>changePermission</permission>
</allow>
</access>
<dataset> <title>Juvenile Herring Growth and Habitats - [UNFORMATTED]</title>
 <creator id="1375466874537"><individualName><salutation>Dr.</salutation>
 <givenName>Brenda</givenName>
 <surName>Norcross</surName>
 </individualName>
 <organizationName>School of Fishries &amp; Ocean Sciences, Univeristy of Alaska, Fairbanks</organizationName>
 <positionName>Professor</positionName>
 <address><deliveryPoint>P.O. Box 757220</deliveryPoint>
 <deliveryPoint>245 O'Neill SFOS/UAF</deliveryPoint>
 <city>Fairbanks</city>
 <administrativeArea>AK</administrativeArea>
 <postalCode>99775-7220</postalCode>
 <country>USA</country>
 </address>
 <phone phonetype="voice">(907) 474-7990</phone>
 <phone phonetype="fax">(907) 474-1943</phone>
 <electronicMailAddress>bnorcross@alaska.edu</electronicMailAddress>
 </creator>
 <creator id="1375467619300"><individualName><salutation>Dr.</salutation>
 <givenName>Evelyn</givenName>
 <surName>Brown</surName>
 </individualName>
 <organizationName>Alaska Department of Fish &amp; Game</organizationName>
 <positionName>Fisheries Bilogist (formerly)</positionName>
 <electronicMailAddress>edb5314@gmail.com</electronicMailAddress>
 </creator>
 <associatedParty><references>1375466874537</references>
 <role>Principal Investigator</role>
 </associatedParty>
 <associatedParty><references>1375467619300</references>
 <role>Author</role>
 </associatedParty>
 <associatedParty id="1375468467260"><individualName><salutation>Dr.</salutation>
 <givenName>Robert</givenName>
 <surName>Foy</surName>
 </individualName>
 <organizationName>Northwest Marine Fisheries Service, National Oceanic &amp; Atmospheric Adminstration</organizationName>
 <positionName>Kodiak Lab Director, Supervisory Research Fishery Biologist</positionName>
 <address><deliveryPoint>AFSC Kodiak Laboratory</deliveryPoint>
 <deliveryPoint>301 Research Court</deliveryPoint>
 <city>Kodiak</city>
 <administrativeArea>AK</administrativeArea>
 <postalCode>99615</postalCode>
 <country>USA</country>
 </address>
 <phone phonetype="voice">907-481-1711</phone>
 <electronicMailAddress>robert.foy@noaa.gov</electronicMailAddress>
 <role>Author</role>
 </associatedParty>
 <associatedParty id="1375468841078"><individualName><givenName>Michele</givenName>
 <surName>Frandsen</surName>
 </individualName>
 <organizationName>Alsak Sea Grant</organizationName>
 <positionName>Program Manager</positionName>
 <phone phonetype="voice">(907) 474-7088</phone>
 <electronicMailAddress>frandsen@ims.uaf.edu</electronicMailAddress>
 <role>Author</role>
 </associatedParty>
 <associatedParty id="1375469057115"><individualName><givenName>Judy</givenName>
 <surName>Seitz</surName>
 </individualName>
 <organizationName>Alaska Coastal Currents</organizationName>
 <positionName>Producer/Reporter</positionName>
 <role>Author</role>
 </associatedParty>
 <associatedParty id="1375469396520"><individualName><salutation>Dr.</salutation>
 <givenName>Kevin</givenName>
 <surName>Stokesbury</surName>
 </individualName>
 <organizationName>University of Massachusetts, Dartmouth</organizationName>
 <positionName>SMS Professor and Professor at UMD</positionName>
 <phone phonetype="voice">508-910-6373</phone>
 <electronicMailAddress>kstokesbury@umassd.edu</electronicMailAddress>
 <role>Author</role>
 </associatedParty>
 <abstract><para>Description of umbrella "Juvenile Herring Growth and Habitats project":

Aerial surveys typically lack precision and are not sufficiently accurate to provide a standalone estimate of stock biomass (Krebs 1989; Gunderson 1993; Hunter and Chumside, 1995). Varia estimate of stock biomass (Krebs 1989; Gunderson 1993; Hunter and Chumside, 1995).  Variability due to sighting conditions, changes in vertical distribution of fish schools, and surveyor bias largely go unmeasured (Hunter and Chumside, 1995). It is therefore important to standardizea s manys urveyp arameters,s ucha s aircraft speed, altitude, time of day, etc., that can affect aeriale stimates(Caughleye t al., 1976).Thus, the main purpose of this study was to develop methodology and improve the precision of visual aerial survey estimates of surface schooling forage fish distribution and abundance. The specific objectives were to: 1) develop an appropriate survey design incorporating estimation of detection error and surveyor bias and defining optimal survey constraints, 2) determine the accuracy of fish species and age class discrimination from visual aerial observations, 3) determine the repeatability of aerial measurements, and 4) determine the spatial resolution of aerial measurements needed to use the results in ecological analyses.  A secondary objective was to develop abundance estimates for jellyfish aggregations (Aequorea sp.) and foraging sea birds. This study demonstrates that aerial surveys are a useful tool for ecological research of forage fish, sea birds, and other marine species. In addition, surveyors can discriminate forage fish species and produce repeatable results with an acceptable level of error. The methods described in this report outline an efficient, cost effective
way to obtain information on the distribution and abundance of forage fish and their predators. In addition, we have identified a model and the sources of error affecting the accuracy and precision of survey results. (from EVOSTC project #320-T final report)

***This work is part of a multi-reseracher, multi-project study of forage fish ecology and surving. The data here include tucker trawl larval surveys. Other data for this project can be referenced in the following packages: df35d.93.12 (http://evos.nceas.ucsb.edu/evos/metacat/df35d.93.12/default).

The hypothesis that juvenile herring aggregated within bays was tested by examining the relationship between the spatial distributions of herring and distances from shore. A group of data cells was considered to be a fish school if the sum of the differences between latitudes and longitudes of adjacent cells was &gt;0.009'. Visual examination of the echograms and plots of cells along transects supported this assumption. Bays were statistically defined from passages or open coast line by creating a parameter that is the
sum of the three nearest shore distances (sum3NSD), each separated by 90". This measurement was calculated at 12 bays and along 2 passages, 26 inside bays and 17 outside bays, to verify that it accurately defined bays, passages, and open coast line. The sum3NSD for each herrin g school within each size mode was calculated and compared to the same measurements from randomly selected points along the transect for the three surveys usinga chi-squared test. Expected values were grouped according to Cochran's rule (Sokal &amp; Rohlf 198 1). This technique corrected sampling and shoreline structure biases, for example 80 % of the shoreline may have been in bays or we may have surveyed bays more than open coastline or passages. Further to determine if there were physical differences in water mass and larval fish community structure at these locations vertical water profiles measuring temperature and salinity at 1 m intervals, using a SeaBird instrument, and two tucker trawl samples (1 m^2 mouth, 505 micronmeter mesh nets) were collected at each of these sites. Tucker trawl samples were preserved in 10% formalin for &gt;48 h, then transferred to 50% isopropyl alcohol and sorted to species and measured in the laboratory.</para>
 </abstract>
 <keywordSet><keyword>Pacific herring</keyword>
 <keyword>Clupea pallasi</keyword>
 <keyword>juvenile</keyword>
 <keyword>larvae</keyword>
 <keyword>Prince William Sound</keyword>
 <keyword>Outer Kenai</keyword>
 <keyword>nursery areas</keyword>
 <keyword>Pacific herring spawn</keyword>
 <keyword>forage fish</keyword>
 <keyword>Pacific sand lance</keyword>
 <keyword>capelin</keyword>
 <keyword>eulachon</keyword>
 <keyword>traditional ecological knowledge</keyword>
 <keyword>local knowledge</keyword>
 <keyword>distribution</keyword>
 </keywordSet>
 <keywordSet><keyword>EVOSTC</keyword>
 <keyword>Exxon Valdez Oil Spill Trustee Council</keyword>
 <keyword>Oil Spill</keyword>
 <keyword>Exxon Valdez</keyword>
 <keyword>Alaska</keyword>
 <keyword>Environmental Drivers</keyword>
 <keyword>Pelagic</keyword>
 <keyword>Fish</keyword>
 <keyword>Oil and Contaminants</keyword>
 <keywordThesaurus>Gulf Watch Alaska Thesaurus</keywordThesaurus>
 </keywordSet>
 <intellectualRights><para>This material is based upon work funded by the Exxon Valdez Oil Spill Trustee Council.  Any opinions, findings, conclusions, or recommendations expressed herein are those of the author(s) and do not necessarily reflect the views or positions of the Trustee Council.
 
Standard scientific norms for attribution and credit to the Exxon Valdez Oil Spill Trustee Council and any additional funding agencies should be followed when using this data. 
 
This data is licensed under CC0. The person who associated a work with this deed has dedicated the work to the public domain by waiving all of his or her rights to the work worldwide under copyright law, including all related and neighboring rights, to the extent allowed by law. You can copy, modify, distribute and perform the work, even for commercial purposes, all without asking permission.</para>
 </intellectualRights>
 <coverage><geographicCoverage><geographicDescription>Prince William Sound, Alaska</geographicDescription>
 <boundingCoordinates><westBoundingCoordinate>-152.62762</westBoundingCoordinate>
 <eastBoundingCoordinate>-145.99754</eastBoundingCoordinate>
 <northBoundingCoordinate>61.12401</northBoundingCoordinate>
 <southBoundingCoordinate>58.50127</southBoundingCoordinate>
 </boundingCoordinates>
 </geographicCoverage>
 <taxonomicCoverage><taxonomicClassification><taxonRankName>Genus</taxonRankName>
 <taxonRankValue>Ammodytes</taxonRankValue>
 <taxonomicClassification><taxonRankName>Species</taxonRankName>
 <taxonRankValue>hexapterus</taxonRankValue>
 <commonName>salmon</commonName>
 </taxonomicClassification>
 </taxonomicClassification>
 <taxonomicClassification><taxonRankName>Genus</taxonRankName>
 <taxonRankValue>Clupea</taxonRankValue>
 <taxonomicClassification><taxonRankName>Species</taxonRankName>
 <taxonRankValue>pallasi</taxonRankValue>
 </taxonomicClassification>
 </taxonomicClassification>
 <taxonomicClassification><taxonRankName>Genus</taxonRankName>
 <taxonRankValue>Mollotus</taxonRankValue>
 <taxonomicClassification><taxonRankName>Species</taxonRankName>
 <taxonRankValue>villosus</taxonRankValue>
 <commonName>Pacific sand lance</commonName>
 </taxonomicClassification>
 </taxonomicClassification>
 <taxonomicClassification><taxonRankName>Genus</taxonRankName>
 <taxonRankValue>Onchohynchus</taxonRankValue>
 <taxonomicClassification><taxonRankName>Species</taxonRankName>
 <taxonRankValue>sp</taxonRankValue>
 <commonName>Pacific herring</commonName>
 </taxonomicClassification>
 </taxonomicClassification>
 <taxonomicClassification><taxonRankName>Genus</taxonRankName>
 <taxonRankValue>Thaleichthys</taxonRankValue>
 <taxonomicClassification><taxonRankName>Species</taxonRankName>
 <taxonRankValue>pacificus</taxonRankValue>
 <commonName>eulachon</commonName>
 </taxonomicClassification>
 </taxonomicClassification>
 </taxonomicCoverage>
 </coverage>
 <contact><references>1375467619300</references>
 </contact>
 <methods><methodStep><description><section><title>Tucker trawl surveys</title>
 <para>To determine if there were physical differences in water mass and larval fish community structure at these locations vertical water profiles measuring temperature and salinity at 1 m intervals, using a SeaBird instrument, and two tucker trawl samples (1 m^2 mouth, 505micron mesh nets) were collected at each of these sites. Tucker trawl samples were preserved in 10% formalin for &gt;48 h, then transferred to 50% isopropyl acholol and sorted to species and measured in the laboratory.</para>
 </section>
 </description>
 <instrumentation>Tucker trawl (1m^2, 505micron mesh)</instrumentation>
 <instrumentation>SeaBird Instrument</instrumentation>
 </methodStep>
 </methods>
 <project><title>Sound Ecosystem Assessment</title>
 <personnel><references>1375466874537</references>
 <role>Principal Investigator</role>
 </personnel>
 <funding><para>Exxon Valdez Oil Spill Trustee Council project number 320 (320-T),</para>
 </funding>
 </project>
 <otherEntity><entityName>larvalData.zip</entityName>
 <entityDescription>Tucker trawl larval data</entityDescription>
 <physical><objectName>larvalData.zip</objectName>
 <size unit="byte">312275</size>
 <dataFormat><externallyDefinedFormat><formatName>application/octet-stream</formatName>
 </externallyDefinedFormat>
 </dataFormat>
 <distribution id="1375480589377"><online><url function="download">ecogrid://knb/df35b.94.1</url>
 </online>
 </distribution>
 </physical>
 <entityType>Other</entityType>
 </otherEntity>
 </dataset>
 </ns0:eml>