<ns0:eml xmlns:ns0="eml://ecoinformatics.org/eml-2.1.1" xmlns:xsi="http://www.w3.org/2001/XMLSchema-instance" packageId="df35d.248.5" system="knb" xsi:schemaLocation="eml://ecoinformatics.org/eml-2.1.1 eml.xsd"> <access authSystem="knb" order="allowFirst"><allow><principal>public</principal>
 <permission>read</permission>
 </allow>
 <allow><principal>cn=evos,o=NCEAS,dc=ecoinformatics,dc=org</principal>
 <permission>all</permission>
 </allow>
 </access>
 <dataset>  <title>Factors affecting recovery of pigeon guillemot populations in Prince William Sound, Alaska 1995 - 2000 [Unformatted Data]</title>
<creator id="1375813675348"> <individualName><givenName>Lindsey</givenName>
 <surName>Hayes</surName>
 </individualName>
 <organizationName>US Fish and Wildlife Service</organizationName>
 </creator>
 <creator id="1375813807609"><individualName><givenName>Gregory</givenName>
 <surName>Golet</surName>
 </individualName>
 <organizationName>The Nature Conservancy</organizationName>
 <electronicMailAddress>ggolet@TNC.ORG</electronicMailAddress>
 </creator>
 <creator id="1375813849680"><individualName><givenName>Kathy</givenName>
 <surName>Kuletz</surName>
 </individualName>
 <organizationName>US Fish and Wildlife Service</organizationName>
 <address><city>Anchorage</city>
 <administrativeArea>Alaska</administrativeArea>
 <country>USA</country>
 </address>
 <electronicMailAddress>Kathy_Kuletz@fws.gov</electronicMailAddress>
 </creator>
 <creator id="1375813969997"><individualName><givenName>David</givenName>
 <surName>Duffy</surName>
 </individualName>
 </creator>
 <creator id="1375813982669"><individualName><givenName>David</givenName>
 <surName>Irons</surName>
 </individualName>
 </creator>
 <creator id="1375813991604"><individualName><givenName>Daniel</givenName>
 <surName>Roby</surName>
 </individualName>
 <organizationName>Oregon State University</organizationName>
 <positionName>Professor</positionName>
 <electronicMailAddress>daniel.roby@oregonstate.edu</electronicMailAddress>
 </creator>
 <creator id="1375814058921"><individualName><givenName>Ted</givenName>
 <surName>Spencer</surName>
 </individualName>
 </creator>
 <associatedParty id="1375814109978"><individualName><givenName>Sarah</givenName>
 <surName>Clark</surName>
 </individualName>
 <organizationName>National Center for Ecological Analysis and Synthesis</organizationName>
 <positionName>Projects Data Coordinator</positionName>
 <address><deliveryPoint>735 State Street, Suite 300</deliveryPoint>
 <city>Santa Barbara</city>
 <administrativeArea>California</administrativeArea>
 <postalCode>93101</postalCode>
 </address>
 <phone phonetype="voice">805-892-2500</phone>
 <electronicMailAddress>sclark@nceas.ucsb.edu</electronicMailAddress>
 <role>Metadata Provider</role>
 </associatedParty>
<abstract><para>The objective of this component was to evaluate the breeding and feeding ecology of pigeon guillemots (Cepphus columba) with respect to the abundance and availability of forage fish in the near shore environment. We monitored the reproductive success of 50 guillemot nests at Naked Island, Prince William Sound. Data from numerous sources indicate that there has been a change in the Gulf of Alaska marine ecosystem that began around the late 1970s, which in turn has probably affected marine bird populations. The population of pigeon guillemots in Prince William Sound decreased from about 15,000 in the early 1970s to less than 5,000 in the 1990s. Study colonies at Naked Island and four neighboring islands in Prince William Sound have shown a similar trend since the late 1970s. During this period, the diet of pigeon guillemot chicks on Naked Island also changed. In the late 1970s Pacific sand lance (Ammodytes hexaptenu), a schooling forage fish, dominated the chick diet. In the 1990s chick diet has been dominated by fish that live on or near the bottom, such as gunnels, pricklebacks, sculpins, and cod-like fish. The correlation between percent sand lance in the chick diet and the total guillemot population is strong, and we suggest that there is a link between the change in diet and the population decline. 

Previous related projects have been funded by the Trustee Council. Oakley and Kuletz (1996) undertook a study in 1989-1990 to compare various population and reproductive parameters of pigeon guillemots before (Oakley and Kuletz 1979, Kuletz 1981, 1983, Oakley 1981) and after the spill. Also, Project 93034, an extensive survey of pigeon guillemot colonies throughout Prince William Sound, was conducted during the summer of 1993 (Sanger and Cody 1994).</para>
</abstract>
<keywordSet><keyword>predation</keyword>
<keyword>population</keyword>
<keyword>prince william sound</keyword>
<keyword>breeding ecology</keyword>
<keyword>ammodytes hexapterus</keyword>
<keyword>cepphus columba</keyword>
<keyword>foraging ecology</keyword>
<keyword>Naked Island</keyword>
<keyword>pigeon guillemot</keyword>
<keyword>sand lance</keyword>
</keywordSet>
<keywordSet><keyword>EVOSTC</keyword>
<keyword>Exxon Valdez Oil Spill Trustee Council</keyword>
<keyword>Oil Spill</keyword>
<keyword>Exxon Valdez</keyword>
<keyword>Alaska</keyword>
<keyword>Pelagic</keyword>
<keyword>Birds</keyword>
<keyword>Fish</keyword>
<keywordThesaurus>Gulf Watch Alaska Thesaurus</keywordThesaurus>
</keywordSet>
<intellectualRights><para>This material is based upon work funded by the Exxon Valdez Oil Spill Trustee Council. Any opinions, findings, conclusions, or recommendations expressed herein are those of the author(s) and do not necessarily reflect the views or positions of the Trustee Council. Standard scientific norms for attribution and credit to the Exxon Valdez Oil Spill Trustee Council and any additional funding agencies should be followed when using these data. Please let the Owner know when these data are used. These data are licensed under CC0. The person who associated a work with this deed has dedicated the work to the public domain by waiving all of his or her rights to the work worldwide under copyright law, including all related and neighboring rights, to the extent allowed by law. You can copy, modify, distribute and perform the work, even for commercial purposes, all without asking permission.</para>
</intellectualRights>
    <coverage><geographicCoverage><geographicDescription>Prince William Sound, Alaska, USA</geographicDescription>
 <boundingCoordinates><westBoundingCoordinate>-149.0</westBoundingCoordinate>
 <eastBoundingCoordinate>-145.5</eastBoundingCoordinate>
 <northBoundingCoordinate>61.25</northBoundingCoordinate>
 <southBoundingCoordinate>59.5</southBoundingCoordinate>
 </boundingCoordinates>
 </geographicCoverage>
 <temporalCoverage><rangeOfDates><beginDate><calendarDate>1995</calendarDate>
 </beginDate>
 <endDate><calendarDate>2000</calendarDate>
 </endDate>
 </rangeOfDates>
 </temporalCoverage>
 <taxonomicCoverage><taxonomicClassification><taxonRankName>Species</taxonRankName>
 <taxonRankValue>Ammodytes hexapterus</taxonRankValue>
 <commonName>Pacific Sand Lance</commonName>
 </taxonomicClassification>
 <taxonomicClassification><taxonRankName>Species</taxonRankName>
 <taxonRankValue>Cepphus columba</taxonRankValue>
 <commonName>Pigeon Guillemot</commonName>
 </taxonomicClassification>
 </taxonomicCoverage>
 </coverage>
 <contact><references>1375813807609</references>
 </contact>
 <methods><methodStep><description><section><title>See Reports</title>
 <para>See PDFs of reports, attached</para>
 </section>
 </description>
 </methodStep>
 </methods>
<project><title>Alaska Predator Ecosystem Project</title>
 <personnel><references>1375813675348</references>
 <role>Principal Investigator</role>
 </personnel>
 <funding><para>Exxon Valdez Oil Spill Trustee Council project numbers 95163-F1, 95163-F, 96163-F, 97163-F, 98163-F, 99163-F, 00163-F</para>
 </funding>
 </project>
  <otherEntity><entityName>originals.zip</entityName>
 <entityDescription>Original files provided by Greg Golet at The Nature Conservancy.</entityDescription>
 <physical><objectName>originals.zip</objectName>
 <size unit="byte">6526547</size>
 <dataFormat><externallyDefinedFormat><formatName>application/octet-stream</formatName>
 </externallyDefinedFormat>
 </dataFormat>
 <distribution id="1375819669667"><online><url function="download">ecogrid://knb/df35d.249.1</url>
 </online>
 </distribution>
 </physical>
 <entityType>Other</entityType>
 </otherEntity>
 <otherEntity><entityName>EXCELexports.zip</entityName>
 <entityDescription>Files exported from various formats (Paradox databases, Quattro Pro tables) to Excel spreadsheets</entityDescription>
 <physical><objectName>EXCELexports.zip</objectName>
 <size unit="byte">7552220</size>
 <dataFormat><externallyDefinedFormat><formatName>application/octet-stream</formatName>
 </externallyDefinedFormat>
 </dataFormat>
 <distribution id="1375819723898"><online><url function="download">ecogrid://knb/df35d.250.1</url>
 </online>
 </distribution>
 </physical>
 <entityType>Other</entityType>
 </otherEntity>
 <otherEntity><entityName>CSV.zip</entityName>
 <entityDescription>Files exported from various formats (Paradox databases, Quattro Pro tables) to CSV files</entityDescription>
 <physical><objectName>CSV.zip</objectName>
 <size unit="byte">1611632</size>
 <dataFormat><externallyDefinedFormat><formatName>application/octet-stream</formatName>
 </externallyDefinedFormat>
 </dataFormat>
 <distribution id="1375819743918"><online><url function="download">ecogrid://knb/df35d.251.1</url>
 </online>
 </distribution>
 </physical>
 <entityType>Other</entityType>
 </otherEntity>
 <otherEntity><entityName>Reports.zip</entityName>
 <entityDescription>PDFs of project reports, including methods and results</entityDescription>
 <physical><objectName>Reports.zip</objectName>
 <size unit="byte">6983264</size>
 <dataFormat><externallyDefinedFormat><formatName>application/octet-stream</formatName>
 </externallyDefinedFormat>
 </dataFormat>
 <distribution id="1377111717345"><online><url function="download">ecogrid://knb/df35d.316.1</url>
 </online>
 </distribution>
 </physical>
 <entityType>Other</entityType>
 </otherEntity>
 </dataset>
 </ns0:eml>