<metadata>
  <idinfo>
    <citation>
      <citeinfo>
        
        <origin>OLIVIER, J.G.</origin>
        

        <title>ISLSCP II EDGAR 3 GRIDDED GREENHOUSE AND OZONE PRECURSOR GAS EMISSIONS</title>

		    
     			<onlink>http://daac.ornl.gov/cgi-bin/dsviewer.pl?ds_id=1022</onlink>
    		
    		
    
        <onlink>http://daac.ornl.gov/mercury_harvest/1022.xml</onlink>
         <alt_onlink>http://daac.ornl.gov/mercury_harvest/1022.xml</alt_onlink>
        
        <onlink>http://daac.ornl.gov//ISLSCP_II/guides/edgar_atmos_emissions_1deg.html</onlink>
        
        
        <geoform>metadata</geoform>
      </citeinfo>
    </citation>
    <descript>
      <abstract>The EDGAR (Emission Database for Global Atmospheric Research) database project is a comprehensive task carried out jointly by the National Institute for Public Health (RIVM) and the Netherlands Organization for Applied Scientific Research (TNO) and stores global emission inventories of direct and indirect greenhouse gases from anthropogenic sources including halocarbons and aerosols both on a per country and region basis as well as on a grid (see http://www.rivm.nl/edgar/). For the ISLSCP Initiative II data collection, gridded global annual anthropogenic emissions for the greenhouse gases CO2, CH4, N2O are provided on a 1.0 degree by 1.0 degree grid for the years 1970, 1980, 1990, and 1995 and for the tropospheric ozone precursor gases CO, NOx, NMVOC (Non-Methane Volatile Organic Compounds) and SO2 for the years 1990 and 1995. There are 2 *.zip data files with this data set.</abstract>
      <supplinf />
    </descript>
    <timeperd>
      <timeinfo>
        <rngdates>
          <begdate>19700101</begdate>
          <enddate>19951231</enddate>
        </rngdates>
      </timeinfo>
    </timeperd>
    <status>
      <progress>Complete</progress>
      <update> As appropriate</update>
    </status>
    <spdom>
      <bounding>
        <westbc>-180</westbc>
        <eastbc>180</eastbc>
        <northbc>90</northbc>
        <southbc>-90</southbc>
      </bounding>
    </spdom>
    <keywords>
      <theme>
        <themekt>Parameter_Sensor_Source</themekt>
        
        <themekey>CARBON AND HYDROCARBON COMPOUNDS|ANALYSIS|COMPUTER MODEL</themekey>
        
        <themekey>EMISSIONS|ANALYSIS|COMPUTER MODEL</themekey>
        
        <themekey>NITROGEN COMPOUNDS|ANALYSIS|COMPUTER MODEL</themekey>
        
        <themekey>SULFUR COMPOUNDS|ANALYSIS|COMPUTER MODEL</themekey>
        
      </theme>
      <theme>
        <themekt>Parameter</themekt>
        
        <themekey>CARBON AND HYDROCARBON COMPOUNDS</themekey>
        
      </theme>
      <theme>
        <themekt>Source</themekt>
        
        <themekey>COMPUTER MODEL</themekey>
        
      </theme>
      <theme>
        <themekt>Sensor</themekt>
        
        <themekey>ANALYSIS</themekey>
        
      </theme>
      
      <place>
        <placekt>Place Keywords</placekt>
        
        <placekey>GLOBAL</placekey>
        
      </place>
    </keywords>
    
    <ptcontac>
      <cntinfo>
        <cntperp>
          <cntper>OLIVIER, J.G.</cntper>
        </cntperp>
        <cntfax>6.1.10.8 Contact Electronic Mail: INTERNET &amp;gt; </cntfax>
      </cntinfo>
    </ptcontac>
  </idinfo>
  <distinfo>
    <distrib>
      <cntinfo>
        <cntperp>
          <cntorg>The Oak Ridge National Laboratory (ORNL) Distributed Active Archive Center (DAAC)</cntorg>
          <cntper>ORNL DAAC User Services Office
        Oak Ridge National Laboratory
        Oak Ridge, Tennessee 37831 USA     
        FAX: +1(865)574-4665</cntper>
        </cntperp>
        <cntvoice>+1(865)241-3952</cntvoice>
        <cntfax>6.1.10.8 Contact Electronic Mail: INTERNET &amp;gt; </cntfax>
        <cntemail>ornldaac@ornl.gov</cntemail>
      </cntinfo>
    </distrib>
    <stdorder>
      <digform>
        <digtopt>
          <onlinopt>
            <computer>http://daac.ornl.gov/</computer>
            <accinstr>PUBLIC</accinstr>
          </onlinopt>
        </digtopt>
      </digform>
    </stdorder>
    <resdesc>Olivier, J.G., 2011. ISLSCP II EDGAR 3 Gridded Greenhouse and Ozone Precursor Gas Emissions. In Hall, Forrest G., G. Collatz, B. Meeson, S. Los, E. Brown de Colstoun, and D. Landis (eds.). ISLSCP Initiative II Collection.  Data set. Available on-line [http://daac.ornl.gov/] from Oak Ridge National Laboratory Distributed Active Archive Center, Oak Ridge, Tennessee, U.S.A.

 doi:10.3334/ORNLDAAC/1022</resdesc>
  </distinfo>
  <metainfo>
    <metd>20110701</metd>
    <metc>
      <cntinfo>
        <cntorgp>
          <cntper>ORNL DAAC Staff</cntper>
        </cntorgp>
        <cntperp>
          <cntper>ORNL DAAC Staff</cntper>
        </cntperp>
        <cntvoice>+1(865)241-3952</cntvoice>
        <cntemail>ornldaac@ornl.gov</cntemail>
      </cntinfo>
    </metc>
    <metstdn>FGDC Content Standard for Digital Geospatial Metadata</metstdn>
  </metainfo>
  <Local-Control-Number>Created 2012 05 22 21 30 32 1331736632 by 160.91.11.44</Local-Control-Number>

  <mercury>
    <begdate>19700101</begdate>
    <enddate>19951231</enddate>
    
    <Site_Information>
      <Site>GLOBAL</Site>
      <Westernmost_Longitude>-180</Westernmost_Longitude>
      <Easternmost_Longitude>180</Easternmost_Longitude>
      <Northernmost_Latitude>90</Northernmost_Latitude>
      <Southernmost_Latitude>-90</Southernmost_Latitude>
    </Site_Information>
    

    
    <Keywords>ISLSCP</Keywords>
    
    <Keywords>METHANE</Keywords>
    
    <Keywords>BIOSPHERE</Keywords>
    
    <Keywords>NOAA CMDL</Keywords>
    
    <Keywords>GRID DATA</Keywords>
    
    <Keywords>LAND COVER</Keywords>
    
    <Keywords>MODEL OUTPUT</Keywords>
    
    <Keywords>AIR POLLUTION</Keywords>
    
    <Keywords>SULFUR DIOXIDE</Keywords>
    
    <Keywords>CARBON DIOXIDE</Keywords>
    
    <Keywords>GREENHOUSE GASES</Keywords>
    
    <Keywords>OZONE PRECURSOR GAS</Keywords>
    
    <Keywords>ANTHROPOGENIC SOURCES</Keywords>
    
    <Keywords>ATMOSPHERIC CHEMISTRY</Keywords>
    
    <Keywords>GLOBAL ENERGY AND WATER CYCLE EXPERIMENT</Keywords>
    
    <Keywords>INTERNATIONAL SATELLITE LAND-SURFACE CLIMATOLOGY PROJECT</Keywords>
    
    
    
    <Parameter_Description>
      <Parameter>CARBON AND HYDROCARBON COMPOUNDS </Parameter>
      <Sensor>ANALYSIS </Sensor>
      <Source>COMPUTER MODEL </Source>
      <Term>ATMOSPHERIC CHEMISTRY </Term>
      <Topic>ATMOSPHERE </Topic>
    </Parameter_Description>
    
    <Parameter_Description>
      <Parameter>EMISSIONS </Parameter>
      <Sensor>ANALYSIS </Sensor>
      <Source>COMPUTER MODEL </Source>
      <Term>AIR QUALITY </Term>
      <Topic>ATMOSPHERE </Topic>
    </Parameter_Description>
    
    <Parameter_Description>
      <Parameter>NITROGEN COMPOUNDS </Parameter>
      <Sensor>ANALYSIS </Sensor>
      <Source>COMPUTER MODEL </Source>
      <Term>ATMOSPHERIC CHEMISTRY </Term>
      <Topic>ATMOSPHERE </Topic>
    </Parameter_Description>
    
    <Parameter_Description>
      <Parameter>SULFUR COMPOUNDS </Parameter>
      <Sensor>ANALYSIS </Sensor>
      <Source>COMPUTER MODEL </Source>
      <Term>ATMOSPHERIC CHEMISTRY </Term>
      <Topic>ATMOSPHERE </Topic>
    </Parameter_Description>
    
    
    
    <Project>ISLSCP II</Project>
    
    
    
    <Navpath>COMPUTER MODEL|ANALYSIS|CARBON AND HYDROCARBON COMPOUNDS</Navpath>
    
    <Navpath>COMPUTER MODEL|ANALYSIS|EMISSIONS</Navpath>
    
    <Navpath>COMPUTER MODEL|ANALYSIS|NITROGEN COMPOUNDS</Navpath>
    
    <Navpath>COMPUTER MODEL|ANALYSIS|SULFUR COMPOUNDS</Navpath>
    
    
    
    <Principal_Investigator>
      <Name>OLIVIER, J.G.</Name>
      <Email />
    </Principal_Investigator>
    
    
    
    <Data_Set_Link>
      <URL>http://daac.ornl.gov/cgi-bin/dsviewer.pl?ds_id=1022</URL>
      <Label>ISLSCP II EDGAR 3 GRIDDED GREENHOUSE AND OZONE PRECURSOR GAS EMISSIONS</Label>
      <Link_Note />
    </Data_Set_Link>
    
  
    
    <Documentation_Link>
      <URL>http://daac.ornl.gov//ISLSCP_II/guides/edgar_atmos_emissions_1deg.html</URL>
      <Label>ISLSCP II EDGAR 3 GRIDDED GREENHOUSE AND OZONE PRECURSOR GAS EMISSIONS</Label>
      <Text />
    </Documentation_Link>
    

    

        

    <OME_Software_Version>/home/web/mercury/write_mercury_xml.pl</OME_Software_Version>
    <OME_DTD_Version>mercury21.dtd</OME_DTD_Version>

    
    <Contact_Person>
      <Email>ornldaac@ornl.gov</Email>
      <Name>ORNL DAAC User Services Office
        Oak Ridge National Laboratory
        Oak Ridge, Tennessee 37831 USA     
        FAX: +1(865)574-4665</Name>
      <Phone>+1(865)241-3952</Phone>
    </Contact_Person>
    
    
    <Temporal_Resolution />
    <enddate_blank />
    <File_ID>1022</File_ID>
    <MD_Entry_id>ISLSCP_EDGAR_ATMOS</MD_Entry_id>
    

    <Spatial_Extent>64800</Spatial_Extent>

    
    <Search_Text_Link>
      <URL>http://daac.ornl.gov//ISLSCP_II/guides/edgar_atmos_emissions_1deg.html</URL>
      <Label>ISLSCP II EDGAR 3 GRIDDED GREENHOUSE AND OZONE PRECURSOR GAS EMISSIONS</Label>
    </Search_Text_Link>
    

    
    
    <Granule_Details>
    
    <Granule>
      <Granule_ID>1022_1</Granule_ID>
      <Granule_Title>ISLSCP II EDGAR 3 Gridded Tropospheric Methan (CH4) Emissions Estimates (above 1000m) in 1970</Granule_Title>
      <Westernmost_Longitude>-180</Westernmost_Longitude>
 			<Easternmost_Longitude>180</Easternmost_Longitude>
  		<Northernmost_Latitude>90</Northernmost_Latitude>
   		<Southernmost_Latitude>-90</Southernmost_Latitude>
    	<Start_Date>1970-01-01</Start_Date>
     	<End_Date>1970-12-31</End_Date>
    </Granule>
    
    <Granule>
      <Granule_ID>1022_10</Granule_ID>
      <Granule_Title>ISLSCP II EDGAR 3 Gridded Tropospheric Carbon Dioxide (CO2) Emissions Estimates (above 1000m) in 1995</Granule_Title>
      <Westernmost_Longitude>-180</Westernmost_Longitude>
 			<Easternmost_Longitude>180</Easternmost_Longitude>
  		<Northernmost_Latitude>90</Northernmost_Latitude>
   		<Southernmost_Latitude>-90</Southernmost_Latitude>
    	<Start_Date>1995-01-01</Start_Date>
     	<End_Date>1995-12-31</End_Date>
    </Granule>
    
    <Granule>
      <Granule_ID>1022_11</Granule_ID>
      <Granule_Title>ISLSCP II EDGAR 3 Gridded Tropospheric Carbon Monoxide (CO) Emissions Estimates (above/below 1000m) in 1990</Granule_Title>
      <Westernmost_Longitude>-180</Westernmost_Longitude>
 			<Easternmost_Longitude>180</Easternmost_Longitude>
  		<Northernmost_Latitude>90</Northernmost_Latitude>
   		<Southernmost_Latitude>-90</Southernmost_Latitude>
    	<Start_Date>1990-01-01</Start_Date>
     	<End_Date>1990-12-31</End_Date>
    </Granule>
    
    <Granule>
      <Granule_ID>1022_12</Granule_ID>
      <Granule_Title>ISLSCP II EDGAR 3 Gridded Tropospheric Carbon Monoxide (CO) Emissions Estimates (above/below 1000m) in 1995</Granule_Title>
      <Westernmost_Longitude>-180</Westernmost_Longitude>
 			<Easternmost_Longitude>180</Easternmost_Longitude>
  		<Northernmost_Latitude>90</Northernmost_Latitude>
   		<Southernmost_Latitude>-90</Southernmost_Latitude>
    	<Start_Date>1995-01-01</Start_Date>
     	<End_Date>1995-12-31</End_Date>
    </Granule>
    
    <Granule>
      <Granule_ID>1022_13</Granule_ID>
      <Granule_Title>ISLSCP II EDGAR 3 Gridded Tropospheric Carbon Monoxide (CO) Emissions Estimates (above 1000m) in 1990</Granule_Title>
      <Westernmost_Longitude>-180</Westernmost_Longitude>
 			<Easternmost_Longitude>180</Easternmost_Longitude>
  		<Northernmost_Latitude>90</Northernmost_Latitude>
   		<Southernmost_Latitude>-90</Southernmost_Latitude>
    	<Start_Date>1990-01-01</Start_Date>
     	<End_Date>1990-12-31</End_Date>
    </Granule>
    
    <Granule>
      <Granule_ID>1022_14</Granule_ID>
      <Granule_Title>ISLSCP II EDGAR 3 Gridded Tropospheric Carbon Monoxide (CO) Emissions Estimates (above 1000m) in 1995</Granule_Title>
      <Westernmost_Longitude>-180</Westernmost_Longitude>
 			<Easternmost_Longitude>180</Easternmost_Longitude>
  		<Northernmost_Latitude>90</Northernmost_Latitude>
   		<Southernmost_Latitude>-90</Southernmost_Latitude>
    	<Start_Date>1995-01-01</Start_Date>
     	<End_Date>1995-12-31</End_Date>
    </Granule>
    
    <Granule>
      <Granule_ID>1022_15</Granule_ID>
      <Granule_Title>ISLSCP II EDGAR 3 Gridded Tropospheric Nitrous Oxide (N2O) Emissions Estimates (above 1000m) in 1970</Granule_Title>
      <Westernmost_Longitude>-180</Westernmost_Longitude>
 			<Easternmost_Longitude>180</Easternmost_Longitude>
  		<Northernmost_Latitude>90</Northernmost_Latitude>
   		<Southernmost_Latitude>-90</Southernmost_Latitude>
    	<Start_Date>1970-01-01</Start_Date>
     	<End_Date>1970-12-31</End_Date>
    </Granule>
    
    <Granule>
      <Granule_ID>1022_16</Granule_ID>
      <Granule_Title>ISLSCP II EDGAR 3 Gridded Tropospheric Nitrous Oxide (N2O) Emissions Estimates (above 1000m) in 1980</Granule_Title>
      <Westernmost_Longitude>-180</Westernmost_Longitude>
 			<Easternmost_Longitude>180</Easternmost_Longitude>
  		<Northernmost_Latitude>90</Northernmost_Latitude>
   		<Southernmost_Latitude>-90</Southernmost_Latitude>
    	<Start_Date>1980-01-01</Start_Date>
     	<End_Date>1980-12-31</End_Date>
    </Granule>
    
    <Granule>
      <Granule_ID>1022_17</Granule_ID>
      <Granule_Title>ISLSCP II EDGAR 3 Gridded Tropospheric Nitrous Oxide (N2O) Emissions Estimates (above 1000m) in 1990</Granule_Title>
      <Westernmost_Longitude>-180</Westernmost_Longitude>
 			<Easternmost_Longitude>180</Easternmost_Longitude>
  		<Northernmost_Latitude>90</Northernmost_Latitude>
   		<Southernmost_Latitude>-90</Southernmost_Latitude>
    	<Start_Date>1990-01-01</Start_Date>
     	<End_Date>1990-12-31</End_Date>
    </Granule>
    
    <Granule>
      <Granule_ID>1022_18</Granule_ID>
      <Granule_Title>ISLSCP II EDGAR 3 Gridded Tropospheric Nitrous Oxide (N2O) Emissions Estimates (above 1000m) in 1995</Granule_Title>
      <Westernmost_Longitude>-180</Westernmost_Longitude>
 			<Easternmost_Longitude>180</Easternmost_Longitude>
  		<Northernmost_Latitude>90</Northernmost_Latitude>
   		<Southernmost_Latitude>-90</Southernmost_Latitude>
    	<Start_Date>1995-01-01</Start_Date>
     	<End_Date>1995-12-31</End_Date>
    </Granule>
    
    <Granule>
      <Granule_ID>1022_19</Granule_ID>
      <Granule_Title>ISLSCP II EDGAR 3 Gridded Tropospheric NMVOC (NMV) Emissions Estimates (above/below 1000m) in 1990</Granule_Title>
      <Westernmost_Longitude>-180</Westernmost_Longitude>
 			<Easternmost_Longitude>180</Easternmost_Longitude>
  		<Northernmost_Latitude>90</Northernmost_Latitude>
   		<Southernmost_Latitude>-90</Southernmost_Latitude>
    	<Start_Date>1990-01-01</Start_Date>
     	<End_Date>1990-12-31</End_Date>
    </Granule>
    
    <Granule>
      <Granule_ID>1022_2</Granule_ID>
      <Granule_Title>ISLSCP II EDGAR 3 Gridded Tropospheric Methan (CH4) Emissions Estimates (above 1000m) in 1980</Granule_Title>
      <Westernmost_Longitude>-180</Westernmost_Longitude>
 			<Easternmost_Longitude>180</Easternmost_Longitude>
  		<Northernmost_Latitude>90</Northernmost_Latitude>
   		<Southernmost_Latitude>-90</Southernmost_Latitude>
    	<Start_Date>1980-01-01</Start_Date>
     	<End_Date>1980-12-31</End_Date>
    </Granule>
    
    <Granule>
      <Granule_ID>1022_20</Granule_ID>
      <Granule_Title>ISLSCP II EDGAR 3 Gridded Tropospheric NMVOC (NMV) Emissions Estimates (above/below 1000m) in 1995</Granule_Title>
      <Westernmost_Longitude>-180</Westernmost_Longitude>
 			<Easternmost_Longitude>180</Easternmost_Longitude>
  		<Northernmost_Latitude>90</Northernmost_Latitude>
   		<Southernmost_Latitude>-90</Southernmost_Latitude>
    	<Start_Date>1995-01-01</Start_Date>
     	<End_Date>1995-12-31</End_Date>
    </Granule>
    
    <Granule>
      <Granule_ID>1022_21</Granule_ID>
      <Granule_Title>ISLSCP II EDGAR 3 Gridded Tropospheric NMVOC (NMV) Emissions Estimates (above 1000m) in 1990</Granule_Title>
      <Westernmost_Longitude>-180</Westernmost_Longitude>
 			<Easternmost_Longitude>180</Easternmost_Longitude>
  		<Northernmost_Latitude>90</Northernmost_Latitude>
   		<Southernmost_Latitude>-90</Southernmost_Latitude>
    	<Start_Date>1990-01-01</Start_Date>
     	<End_Date>1990-12-31</End_Date>
    </Granule>
    
    <Granule>
      <Granule_ID>1022_22</Granule_ID>
      <Granule_Title>ISLSCP II EDGAR 3 Gridded Tropospheric NMVOC (NMV) Emissions Estimates (above 1000m) in 1995</Granule_Title>
      <Westernmost_Longitude>-180</Westernmost_Longitude>
 			<Easternmost_Longitude>180</Easternmost_Longitude>
  		<Northernmost_Latitude>90</Northernmost_Latitude>
   		<Southernmost_Latitude>-90</Southernmost_Latitude>
    	<Start_Date>1995-01-01</Start_Date>
     	<End_Date>1995-12-31</End_Date>
    </Granule>
    
    <Granule>
      <Granule_ID>1022_23</Granule_ID>
      <Granule_Title>ISLSCP II EDGAR 3 Gridded Tropospheric Nitrogen Dioxide (NOX) Emissions Estimates (above/below 1000m) in 1990</Granule_Title>
      <Westernmost_Longitude>-180</Westernmost_Longitude>
 			<Easternmost_Longitude>180</Easternmost_Longitude>
  		<Northernmost_Latitude>90</Northernmost_Latitude>
   		<Southernmost_Latitude>-90</Southernmost_Latitude>
    	<Start_Date>1990-01-01</Start_Date>
     	<End_Date>1990-12-31</End_Date>
    </Granule>
    
    <Granule>
      <Granule_ID>1022_24</Granule_ID>
      <Granule_Title>ISLSCP II EDGAR 3 Gridded Tropospheric Nitrogen Dioxide (NOX) Emissions Estimates (above/below 1000m) in 1995</Granule_Title>
      <Westernmost_Longitude>-180</Westernmost_Longitude>
 			<Easternmost_Longitude>180</Easternmost_Longitude>
  		<Northernmost_Latitude>90</Northernmost_Latitude>
   		<Southernmost_Latitude>-90</Southernmost_Latitude>
    	<Start_Date>1995-01-01</Start_Date>
     	<End_Date>1995-12-31</End_Date>
    </Granule>
    
    <Granule>
      <Granule_ID>1022_25</Granule_ID>
      <Granule_Title>ISLSCP II EDGAR 3 Gridded Tropospheric Nitrogen Dioxide (NOX) Emissions Estimates (above 1000m) in 1990</Granule_Title>
      <Westernmost_Longitude>-180</Westernmost_Longitude>
 			<Easternmost_Longitude>180</Easternmost_Longitude>
  		<Northernmost_Latitude>90</Northernmost_Latitude>
   		<Southernmost_Latitude>-90</Southernmost_Latitude>
    	<Start_Date>1990-01-01</Start_Date>
     	<End_Date>1990-12-31</End_Date>
    </Granule>
    
    <Granule>
      <Granule_ID>1022_26</Granule_ID>
      <Granule_Title>ISLSCP II EDGAR 3 Gridded Tropospheric Nitrogen Dioxide (NOX) Emissions Estimates (above 1000m) in 1995</Granule_Title>
      <Westernmost_Longitude>-180</Westernmost_Longitude>
 			<Easternmost_Longitude>180</Easternmost_Longitude>
  		<Northernmost_Latitude>90</Northernmost_Latitude>
   		<Southernmost_Latitude>-90</Southernmost_Latitude>
    	<Start_Date>1995-01-01</Start_Date>
     	<End_Date>1995-12-31</End_Date>
    </Granule>
    
    <Granule>
      <Granule_ID>1022_27</Granule_ID>
      <Granule_Title>ISLSCP II EDGAR 3 Gridded Tropospheric Sulphur Dioxide (SO2) Emissions Estimates (above 1000m) in 1990</Granule_Title>
      <Westernmost_Longitude>-180</Westernmost_Longitude>
 			<Easternmost_Longitude>180</Easternmost_Longitude>
  		<Northernmost_Latitude>90</Northernmost_Latitude>
   		<Southernmost_Latitude>-90</Southernmost_Latitude>
    	<Start_Date>1990-01-01</Start_Date>
     	<End_Date>1990-12-31</End_Date>
    </Granule>
    
    <Granule>
      <Granule_ID>1022_28</Granule_ID>
      <Granule_Title>ISLSCP II EDGAR 3 Gridded Tropospheric Sulphur Dioxide (SO2) Emissions Estimates (above 1000m) in 1995</Granule_Title>
      <Westernmost_Longitude>-180</Westernmost_Longitude>
 			<Easternmost_Longitude>180</Easternmost_Longitude>
  		<Northernmost_Latitude>90</Northernmost_Latitude>
   		<Southernmost_Latitude>-90</Southernmost_Latitude>
    	<Start_Date>1995-01-01</Start_Date>
     	<End_Date>1995-12-31</End_Date>
    </Granule>
    
    <Granule>
      <Granule_ID>1022_3</Granule_ID>
      <Granule_Title>ISLSCP II EDGAR 3 Gridded Tropospheric Methan (CH4) Emissions Estimates (above 1000m) in 1990</Granule_Title>
      <Westernmost_Longitude>-180</Westernmost_Longitude>
 			<Easternmost_Longitude>180</Easternmost_Longitude>
  		<Northernmost_Latitude>90</Northernmost_Latitude>
   		<Southernmost_Latitude>-90</Southernmost_Latitude>
    	<Start_Date>1990-01-01</Start_Date>
     	<End_Date>1990-12-31</End_Date>
    </Granule>
    
    <Granule>
      <Granule_ID>1022_4</Granule_ID>
      <Granule_Title>ISLSCP II EDGAR 3 Gridded Tropospheric Methan (CH4) Emissions Estimates (above 1000m) in 1995</Granule_Title>
      <Westernmost_Longitude>-180</Westernmost_Longitude>
 			<Easternmost_Longitude>180</Easternmost_Longitude>
  		<Northernmost_Latitude>90</Northernmost_Latitude>
   		<Southernmost_Latitude>-90</Southernmost_Latitude>
    	<Start_Date>1995-01-01</Start_Date>
     	<End_Date>1995-12-31</End_Date>
    </Granule>
    
    <Granule>
      <Granule_ID>1022_5</Granule_ID>
      <Granule_Title>ISLSCP II EDGAR 3 Gridded Tropospheric Carbon Dioxide (CO2) Emissions Estimates (above/below 1000m) in 1990</Granule_Title>
      <Westernmost_Longitude>-180</Westernmost_Longitude>
 			<Easternmost_Longitude>180</Easternmost_Longitude>
  		<Northernmost_Latitude>90</Northernmost_Latitude>
   		<Southernmost_Latitude>-90</Southernmost_Latitude>
    	<Start_Date>1990-01-01</Start_Date>
     	<End_Date>1990-12-31</End_Date>
    </Granule>
    
    <Granule>
      <Granule_ID>1022_6</Granule_ID>
      <Granule_Title>ISLSCP II EDGAR 3 Gridded Tropospheric Carbon Dioxide (CO2) Emissions Estimates (above/below 1000m) in 1995</Granule_Title>
      <Westernmost_Longitude>-180</Westernmost_Longitude>
 			<Easternmost_Longitude>180</Easternmost_Longitude>
  		<Northernmost_Latitude>90</Northernmost_Latitude>
   		<Southernmost_Latitude>-90</Southernmost_Latitude>
    	<Start_Date>1995-01-01</Start_Date>
     	<End_Date>1995-12-31</End_Date>
    </Granule>
    
    <Granule>
      <Granule_ID>1022_7</Granule_ID>
      <Granule_Title>ISLSCP II EDGAR 3 Gridded Tropospheric Carbon Dioxide (CO2) Emissions Estimates (above 1000m) in 1970</Granule_Title>
      <Westernmost_Longitude>-180</Westernmost_Longitude>
 			<Easternmost_Longitude>180</Easternmost_Longitude>
  		<Northernmost_Latitude>90</Northernmost_Latitude>
   		<Southernmost_Latitude>-90</Southernmost_Latitude>
    	<Start_Date>1970-01-01</Start_Date>
     	<End_Date>1970-12-31</End_Date>
    </Granule>
    
    <Granule>
      <Granule_ID>1022_8</Granule_ID>
      <Granule_Title>ISLSCP II EDGAR 3 Gridded Tropospheric Carbon Dioxide (CO2) Emissions Estimates (above 1000m) in 1980</Granule_Title>
      <Westernmost_Longitude>-180</Westernmost_Longitude>
 			<Easternmost_Longitude>180</Easternmost_Longitude>
  		<Northernmost_Latitude>90</Northernmost_Latitude>
   		<Southernmost_Latitude>-90</Southernmost_Latitude>
    	<Start_Date>1980-01-01</Start_Date>
     	<End_Date>1980-12-31</End_Date>
    </Granule>
    
    <Granule>
      <Granule_ID>1022_9</Granule_ID>
      <Granule_Title>ISLSCP II EDGAR 3 Gridded Tropospheric Carbon Dioxide (CO2) Emissions Estimates (above 1000m) in 1990</Granule_Title>
      <Westernmost_Longitude>-180</Westernmost_Longitude>
 			<Easternmost_Longitude>180</Easternmost_Longitude>
  		<Northernmost_Latitude>90</Northernmost_Latitude>
   		<Southernmost_Latitude>-90</Southernmost_Latitude>
    	<Start_Date>1990-01-01</Start_Date>
     	<End_Date>1990-12-31</End_Date>
    </Granule>
    
    </Granule_Details>
    <OGC_URL>http://webmap.ornl.gov/wcsdown/dataset.jsp?ds_id=1022</OGC_URL>
    <THREDDS_URL>http://thredds.daac.ornl.gov/thredds/catalog/1022/</THREDDS_URL>


  </mercury>

</metadata>