<ns0:systemMetadata xmlns:ns0="http://ns.dataone.org/service/types/v1"><serialVersion>1</serialVersion><identifier>ark:/13030/m5b56jdg/3/cadwsap-s0900636-001.xml</identifier><formatId>FGDC-STD-001-1998</formatId><size>4961</size><checksum algorithm="SHA-1">8b2e29535e377a00e713fb81aebd0dfc41739393</checksum><submitter>uid=mreyes,o=CDL,dc=cdlib,dc=org</submitter><rightsHolder>ark:/13030/j2z317tt</rightsHolder><accessPolicy><allow><subject>public</subject><permission>read</permission></allow></accessPolicy><replicationPolicy replicationAllowed="false" /><archived>false</archived><dateUploaded>2014-10-16T21:40:59.374+00:00</dateUploaded><dateSysMetadataModified>2014-10-17T03:32:14.632+00:00</dateSysMetadataModified><originMemberNode>urn:node:CDL</originMemberNode><authoritativeMemberNode>urn:node:CDL</authoritativeMemberNode><replica><replicaMemberNode>urn:node:CDL</replicaMemberNode><replicationStatus>completed</replicationStatus><replicaVerified>2014-10-17T03:32:07.885+00:00</replicaVerified></replica><replica><replicaMemberNode>urn:node:CN</replicaMemberNode><replicationStatus>completed</replicationStatus><replicaVerified>2014-10-17T03:32:07.941+00:00</replicaVerified></replica></ns0:systemMetadata>