<metadata xmlns:ns0="http://purl.org/ornl/schema/mercury/terms/v1.0" xmlns:xsi="http://www.w3.org/2001/XMLSchema-instance" xsi:schemaLocation="http://purl.org/ornl/schema/mercury/terms/v1.0 mercury-ornl-v1.xsd">
  <idinfo>
    <citation>
      <citeinfo>
        <origin>van Woerden, Jaap</origin>
        <title>Global Environmental Outlook (GEO) Data Portal</title>
        <onlink>http://daac.ornl.gov/metadata/bluangel_harvest/RGED/curtis/metadata/landuse/geo_data_portal.xml</onlink>
        <alt_onlink>http://daac.ornl.gov/metadata/bluangel_harvest/RGED/curtis/metadata/landuse/geo_data_portal.xml</alt_onlink>
        <onlink>http://www.unep.org/GEO/index.htm</onlink>
        <onlink>http://www.unep.org/GEO/geo3/</onlink>
        <onlink>http://geocompendium.grid.unep.ch/</onlink>
        <onlink />
      </citeinfo>
    </citation>
    <descript>
      <abstract>The Global Environment Outlook (GEO) Data Portal was initiated in October 2000 to provide a comprehensive, reliable, and timely supply of data sets used by the United Nations Environment Programme (UNEP) and its partners in the GEO reports and other integrated environment assessments. Since then, the GEO Data Portal has matured into a unique data and information application which responds to the needs of the global environmental community for easy access to systematic and well-documented data on the environment, including the state of natural resources, as well as the societal driving forces and root causes of environmental change and degradation.

The GEO Data Portal is managed by DEWA/GRID-Geneva which is part of UNEP's global network of environmental information centres, known as the Global Resource Information Database (GRID).
 
The GEO Data Portal's online database holds more than 700 data sets representing over 400 unique variables.  Data are provided as national, subregional, regional and global statistics or as geospatial data sets (maps), covering themes like Freshwater, Population, Forests, Emissions, Climate, Disasters, Health, and Gross Domestic Product (GDP). The data cover the time period from 1972-2002 where available. The GEO Data Portal offers users the option to: (1) draw, view and explore maps, graphs and tables online; (2) view documentation and other metadata; and/or (3) download data sets as Excel, PDF, CSV, XML or ARCINFO Shape files as appropriate. 

Data from the GEO Data Portal are extracted by UNEP/DEWA/GRID-Geneva to produce another product, called the GEO-3 Data Compendium.  The Compendium provides the major statistical data sets underlying the integrated analyses in the GEO reports. It is available online at [http://geocompendium.grid.unep.ch/] as well as on CD-ROM and as a printed publication. 

The latest GEO report is GEO-3. This third edition complements the detailed assessment of the state of the global environment set out in GEO-2000. 

The data sets held in the GEO Data Portal are derived from many different organizations and databases. These sources are listed at [http://geodata.grid.unep.ch/datasource.php].  In addition to providing readily available data sets, several institutions also have assisted in data processing. The data sources and providers are listed in the metadata that accompany each data set.</abstract>
      <supplinf />
    </descript>
    <timeperd>
      <timeinfo>
        <rngdates>
          <begdate>19720101</begdate>
          <enddate />
        </rngdates>
      </timeinfo>
    </timeperd>
    <status>
      <progress>Ongoing</progress>
      <update>As appropriate</update>
    </status>
    <spdom>
      <bounding>
        <westbc>-180</westbc>
        <eastbc>180</eastbc>
        <northbc>90</northbc>
        <southbc>-90</southbc>
      </bounding>
    </spdom>
    <keywords>
      <theme>
        <themekt>Parameter_Sensor_Source</themekt>
        <themekey>EMISSIONS|VARIOUS|VARIOUS</themekey>
        <themekey>PRECIPITATION AMOUNT|VARIOUS|VARIOUS</themekey>
        <themekey>BIODIVERSITY|VARIOUS|VARIOUS</themekey>
        <themekey>WETLANDS|VARIOUS|VARIOUS</themekey>
        <themekey>MARINE AND COASTAL FISHERIES|VARIOUS|VARIOUS</themekey>
        <themekey>NATURAL DISASTERS|VARIOUS|VARIOUS</themekey>
        <themekey>FOREST HABITAT|VARIOUS|VARIOUS</themekey>
        <themekey>FOREST FIRES|VARIOUS|VARIOUS</themekey>
        <themekey>FOREST PRODUCTS|VARIOUS|VARIOUS</themekey>
        <themekey>GROUNDWATER RECHARGE|VARIOUS|VARIOUS</themekey>
        <themekey>GROUNDWATER WITHDRAWAL|VARIOUS|VARIOUS</themekey>
        <themekey>INTERNAL RENEWABLE WATER RESOURCES|VARIOUS|VARIOUS</themekey>
        <themekey>FRESHWATER FISHERIES PRODUCTION|VARIOUS|VARIOUS</themekey>
        <themekey>WATER USE|VARIOUS|VARIOUS</themekey>
        <themekey>LAND USE|VARIOUS|VARIOUS</themekey>
        <themekey>AGRICULTURAL PRODUCTION|VARIOUS|VARIOUS</themekey>
        <themekey>FERTILIZERS|VARIOUS|VARIOUS</themekey>
        <themekey>PESTICIDES|VARIOUS|VARIOUS</themekey>
        <themekey>TRADE|VARIOUS|VARIOUS</themekey>
        <themekey>ENERGY SUPPLY AND CONSUMPTION|VARIOUS|VARIOUS</themekey>
        <themekey>POPULATION|VARIOUS|VARIOUS</themekey>
        <themekey>TRANSPORTATION|VARIOUS|VARIOUS</themekey>
        <themekey>COMMUNICATIONS|VARIOUS|VARIOUS</themekey>
        <themekey>GROSS DOMESTIC PRODUCT|VARIOUS|VARIOUS</themekey>
        <themekey>VITAL STATISTICS|VARIOUS|VARIOUS</themekey>
        <themekey>ACCESS TO IMPROVED SANITATION AND WATER SUPPLY|VARIOUS|VARIOUS</themekey>
        <themekey>EDUCATIONAL ENROLLMENT/ATTAINMENT|VARIOUS|VARIOUS</themekey>
        <themekey>URBAN POPULATION|VARIOUS|VARIOUS</themekey>
      </theme>
      <theme>
        <themekt>Parameter</themekt>
        <themekey>EMISSIONS</themekey>
      </theme>
      <theme>
        <themekt>Source</themekt>
        <themekey>VARIOUS</themekey>
      </theme>
      <theme>
        <themekt>Sensor</themekt>
        <themekey>VARIOUS</themekey>
      </theme>
      <place>
        <placekt>Place Keywords</placekt>
        <placekey>Global</placekey>
      </place>
    </keywords>
    <ptcontac>
      <cntinfo>
        <cntperp>
          <cntper>van Woerden, Jaap</cntper>
        </cntperp>
        <cntfax>6.1.10.8 Contact Electronic Mail: INTERNET &amp;gt; Woerden@grid.unep.ch</cntfax>
      </cntinfo>
    </ptcontac>
  </idinfo>
  <distinfo>
    <distrib>
      <cntinfo>
        <cntperp>
          <cntorg>Division of Early Warning and Assessment (DEWA), United Nations Environment Programme (UNEP), Geneva, Switzerland</cntorg>
          <cntper>van Woerden, Jaap</cntper>
        </cntperp>
        <cntvoice>+41-22-917-8294</cntvoice>
        <cntfax>6.1.10.8 Contact Electronic Mail: INTERNET &amp;gt; Woerden@grid.unep.ch</cntfax>
        <cntemail>Woerden@grid.unep.ch</cntemail>
      </cntinfo>
    </distrib>
    <stdorder>
      <digform>
        <digtopt>
          <onlinopt>
            <computer>http://geodata.grid.unep.ch/</computer>
            <accinstr>Public</accinstr>
          </onlinopt>
        </digtopt>
      </digform>
    </stdorder>
    <resdesc>Global Environmental Outlook (GEO) Data Portal.  Available online at [http://geodata.grid.unep.ch/] from GRID, Division of Early Warning and Assessment (DEWA), United Nations Environment Programme (UNEP), Geneva, Switzerland.</resdesc>
  </distinfo>
  <metainfo>
    <metd>20061120 153430</metd>
    <metc>
      <cntinfo>
        <cntorgp>
          <cntper>Curtis, Carroll</cntper>
        </cntorgp>
        <cntperp>
          <cntper>Curtis, Carroll</cntper>
        </cntperp>
        <cntvoice>+1-804-769-2495</cntvoice>
        <cntemail>cncurtis@crosslink.net</cntemail>
      </cntinfo>
    </metc>
    <metstdn>FGDC Content Standard for Digital Geospatial Metadata</metstdn>
  </metainfo>
  <mercury>
    <begdate>19720101</begdate>
    <enddate>2014924</enddate>
    <Site_Information>
      <Site>Global</Site>
      <Westernmost_Longitude>-180</Westernmost_Longitude>
      <Easternmost_Longitude>180</Easternmost_Longitude>
      <Northernmost_Latitude>90</Northernmost_Latitude>
      <Southernmost_Latitude>-90</Southernmost_Latitude>
    </Site_Information>
    <Keywords>Africa</Keywords>
    <Keywords>Agricultural lands</Keywords>
    <Keywords>Agricultural production</Keywords>
    <Keywords>Asia</Keywords>
    <Keywords>Atmosphere</Keywords>
    <Keywords>Australia</Keywords>
    <Keywords>Biodiversity</Keywords>
    <Keywords>Coastal fisheries</Keywords>
    <Keywords>Coastal boundaries</Keywords>
    <Keywords>Disasters</Keywords>
    <Keywords>Droughts</Keywords>
    <Keywords>Earthquakes</Keywords>
    <Keywords>Emissions</Keywords>
    <Keywords>Energy</Keywords>
    <Keywords>Energy resources</Keywords>
    <Keywords>Energy supply</Keywords>
    <Keywords>Energy consumption</Keywords>
    <Keywords>EOSDIS</Keywords>
    <Keywords>Europe</Keywords>
    <Keywords>FAO</Keywords>
    <Keywords>Fertilizers</Keywords>
    <Keywords>Fisheries</Keywords>
    <Keywords>Fisheries production</Keywords>
    <Keywords>Forest fires</Keywords>
    <Keywords>Forest products</Keywords>
    <Keywords>Forests</Keywords>
    <Keywords>Floods</Keywords>
    <Keywords>Freshwater</Keywords>
    <Keywords>GEO</Keywords>
    <Keywords>GEO Data Compendium</Keywords>
    <Keywords>GEO Data Portal</Keywords>
    <Keywords>Global Environmental Outlook</Keywords>
    <Keywords>GRID</Keywords>
    <Keywords>Groundwater</Keywords>
    <Keywords>Land use</Keywords>
    <Keywords>Marine fisheries</Keywords>
    <Keywords>North America</Keywords>
    <Keywords>Oceania</Keywords>
    <Keywords>Pesticides</Keywords>
    <Keywords>Population</Keywords>
    <Keywords>Population infrastructure</Keywords>
    <Keywords>Precipitation</Keywords>
    <Keywords>Renewable water resources</Keywords>
    <Keywords>Sanitation</Keywords>
    <Keywords>Socioeconomic indicators</Keywords>
    <Keywords>South America</Keywords>
    <Keywords>Surface water</Keywords>
    <Keywords>Terrestrial habitat</Keywords>
    <Keywords>Urban areas</Keywords>
    <Keywords>Urban population</Keywords>
    <Keywords>Vegetation Collections</Keywords>
    <Keywords>Water supply</Keywords>
    <Keywords>Water use</Keywords>
    <Keywords>Wetlands</Keywords>
    <Parameter_Description>
      <Parameter>EMISSIONS</Parameter>
      <Sensor>VARIOUS</Sensor>
      <Source>VARIOUS</Source>
      <Term>AIR QUALITY</Term>
      <Topic>ATMOSPHERE</Topic>
    </Parameter_Description>
    <Parameter_Description>
      <Parameter>PRECIPITATION AMOUNT</Parameter>
      <Sensor>VARIOUS</Sensor>
      <Source>VARIOUS</Source>
      <Term>PRECIPITATION</Term>
      <Topic>ATMOSPHERE</Topic>
    </Parameter_Description>
    <Parameter_Description>
      <Parameter>BIODIVERSITY</Parameter>
      <Sensor>VARIOUS</Sensor>
      <Source>VARIOUS</Source>
      <Term>ECOLOGICAL DYNAMICS</Term>
      <Topic>BIOSPHERE</Topic>
    </Parameter_Description>
    <Parameter_Description>
      <Parameter>WETLANDS</Parameter>
      <Sensor>VARIOUS</Sensor>
      <Source>VARIOUS</Source>
      <Term>WETLANDS</Term>
      <Topic>BIOSPHERE</Topic>
    </Parameter_Description>
    <Parameter_Description>
      <Parameter>MARINE AND COASTAL FISHERIES</Parameter>
      <Sensor>VARIOUS</Sensor>
      <Source>VARIOUS</Source>
      <Term>MARINE ENVIRONMENT MONITORING</Term>
      <Topic>OCEANS</Topic>
    </Parameter_Description>
    <Parameter_Description>
      <Parameter>NATURAL DISASTERS</Parameter>
      <Sensor>VARIOUS</Sensor>
      <Source>VARIOUS</Source>
      <Term>ENVIRONMENTAL IMPACTS</Term>
      <Topic>HUMAN DIMENSIONS</Topic>
    </Parameter_Description>
    <Parameter_Description>
      <Parameter>FOREST HABITAT</Parameter>
      <Sensor>VARIOUS</Sensor>
      <Source>VARIOUS</Source>
      <Term>TERRESTRIAL HABITAT</Term>
      <Topic>BIOSPHERE</Topic>
    </Parameter_Description>
    <Parameter_Description>
      <Parameter>FOREST FIRES</Parameter>
      <Sensor>VARIOUS</Sensor>
      <Source>VARIOUS</Source>
      <Term>TERRESTRIAL HABITAT</Term>
      <Topic>BIOSPHERE</Topic>
    </Parameter_Description>
    <Parameter_Description>
      <Parameter>FOREST PRODUCTS</Parameter>
      <Sensor>VARIOUS</Sensor>
      <Source>VARIOUS</Source>
      <Term>TERRESTRIAL HABITAT</Term>
      <Topic>BIOSPHERE</Topic>
    </Parameter_Description>
    <Parameter_Description>
      <Parameter>GROUNDWATER RECHARGE</Parameter>
      <Sensor>VARIOUS</Sensor>
      <Source>VARIOUS</Source>
      <Term>GROUND WATER</Term>
      <Topic>HYDROSPHERE</Topic>
    </Parameter_Description>
    <Parameter_Description>
      <Parameter>GROUNDWATER WITHDRAWAL</Parameter>
      <Sensor>VARIOUS</Sensor>
      <Source>VARIOUS</Source>
      <Term>GROUND WATER</Term>
      <Topic>HYDROSPHERE</Topic>
    </Parameter_Description>
    <Parameter_Description>
      <Parameter>INTERNAL RENEWABLE WATER RESOURCES</Parameter>
      <Sensor>VARIOUS</Sensor>
      <Source>VARIOUS</Source>
      <Term>SURFACE WATER</Term>
      <Topic>HYDROSPHERE</Topic>
    </Parameter_Description>
    <Parameter_Description>
      <Parameter>FRESHWATER FISHERIES PRODUCTION</Parameter>
      <Sensor>VARIOUS</Sensor>
      <Source>VARIOUS</Source>
      <Term>AQUATIC HABITAT</Term>
      <Topic>BIOSPHERE</Topic>
    </Parameter_Description>
    <Parameter_Description>
      <Parameter>WATER USE</Parameter>
      <Sensor>VARIOUS</Sensor>
      <Source>VARIOUS</Source>
      <Term>GROUND AND SURFACE WATER</Term>
      <Topic>HYDROSPHERE</Topic>
    </Parameter_Description>
    <Parameter_Description>
      <Parameter>LAND USE</Parameter>
      <Sensor>VARIOUS</Sensor>
      <Source>VARIOUS</Source>
      <Term>LAND USE/LAND COVER</Term>
      <Topic>LAND SURFACE</Topic>
    </Parameter_Description>
    <Parameter_Description>
      <Parameter>AGRICULTURAL PRODUCTION</Parameter>
      <Sensor>VARIOUS</Sensor>
      <Source>VARIOUS</Source>
      <Term>PLANT COMMODITIES</Term>
      <Topic>AGRICULTURE</Topic>
    </Parameter_Description>
    <Parameter_Description>
      <Parameter>FERTILIZERS</Parameter>
      <Sensor>VARIOUS</Sensor>
      <Source>VARIOUS</Source>
      <Term>AGRICULTURAL CHEMICALS</Term>
      <Topic>AGRICULTURE</Topic>
    </Parameter_Description>
    <Parameter_Description>
      <Parameter>PESTICIDES</Parameter>
      <Sensor>VARIOUS</Sensor>
      <Source>VARIOUS</Source>
      <Term>AGRICULTURAL CHEMICALS</Term>
      <Topic>AGRICULTURE</Topic>
    </Parameter_Description>
    <Parameter_Description>
      <Parameter>TRADE</Parameter>
      <Sensor>VARIOUS</Sensor>
      <Source>VARIOUS</Source>
      <Term>ECONOMIC RESOURCES</Term>
      <Topic>HUMAN DIMENSIONS</Topic>
    </Parameter_Description>
    <Parameter_Description>
      <Parameter>ENERGY SUPPLY AND CONSUMPTION</Parameter>
      <Sensor>VARIOUS</Sensor>
      <Source>VARIOUS</Source>
      <Term>ECONOMIC RESOURCES</Term>
      <Topic>HUMAN DIMENSIONS</Topic>
    </Parameter_Description>
    <Parameter_Description>
      <Parameter>POPULATION</Parameter>
      <Sensor>VARIOUS</Sensor>
      <Source>VARIOUS</Source>
      <Term>POPULATION</Term>
      <Topic>HUMAN DIMENSIONS</Topic>
    </Parameter_Description>
    <Parameter_Description>
      <Parameter>TRANSPORTATION</Parameter>
      <Sensor>VARIOUS</Sensor>
      <Source>VARIOUS</Source>
      <Term>INFRASTRUCTURE</Term>
      <Topic>HUMAN DIMENSIONS</Topic>
    </Parameter_Description>
    <Parameter_Description>
      <Parameter>COMMUNICATIONS</Parameter>
      <Sensor>VARIOUS</Sensor>
      <Source>VARIOUS</Source>
      <Term>INFRASTRUCTURE</Term>
      <Topic>HUMAN DIMENSIONS</Topic>
    </Parameter_Description>
    <Parameter_Description>
      <Parameter>GROSS DOMESTIC PRODUCT</Parameter>
      <Sensor>VARIOUS</Sensor>
      <Source>VARIOUS</Source>
      <Term>ECONOMIC RESOURCES</Term>
      <Topic>HUMAN DIMENSIONS</Topic>
    </Parameter_Description>
    <Parameter_Description>
      <Parameter>VITAL STATISTICS</Parameter>
      <Sensor>VARIOUS</Sensor>
      <Source>VARIOUS</Source>
      <Term>HUMAN HEALTH</Term>
      <Topic>HUMAN DIMENSIONS</Topic>
    </Parameter_Description>
    <Parameter_Description>
      <Parameter>ACCESS TO IMPROVED SANITATION AND WATER SUPPLY</Parameter>
      <Sensor>VARIOUS</Sensor>
      <Source>VARIOUS</Source>
      <Term>HUMAN HEALTH</Term>
      <Topic>HUMAN DIMENSIONS</Topic>
    </Parameter_Description>
    <Parameter_Description>
      <Parameter>EDUCATIONAL ENROLLMENT/ATTAINMENT</Parameter>
      <Sensor>VARIOUS</Sensor>
      <Source>VARIOUS</Source>
      <Term>INFRASTRUCTURE</Term>
      <Topic>HUMAN DIMENSIONS</Topic>
    </Parameter_Description>
    <Parameter_Description>
      <Parameter>URBAN POPULATION</Parameter>
      <Sensor>VARIOUS</Sensor>
      <Source>VARIOUS</Source>
      <Term>POPULATION</Term>
      <Topic>HUMAN DIMENSIONS</Topic>
    </Parameter_Description>
    <Project />
    <Navpath>VARIOUS|VARIOUS|EMISSIONS</Navpath>
    <Navpath>VARIOUS|VARIOUS|PRECIPITATION AMOUNT</Navpath>
    <Navpath>VARIOUS|VARIOUS|BIODIVERSITY</Navpath>
    <Navpath>VARIOUS|VARIOUS|WETLANDS</Navpath>
    <Navpath>VARIOUS|VARIOUS|MARINE AND COASTAL FISHERIES</Navpath>
    <Navpath>VARIOUS|VARIOUS|NATURAL DISASTERS</Navpath>
    <Navpath>VARIOUS|VARIOUS|FOREST HABITAT</Navpath>
    <Navpath>VARIOUS|VARIOUS|FOREST FIRES</Navpath>
    <Navpath>VARIOUS|VARIOUS|FOREST PRODUCTS</Navpath>
    <Navpath>VARIOUS|VARIOUS|GROUNDWATER RECHARGE</Navpath>
    <Navpath>VARIOUS|VARIOUS|GROUNDWATER WITHDRAWAL</Navpath>
    <Navpath>VARIOUS|VARIOUS|INTERNAL RENEWABLE WATER RESOURCES</Navpath>
    <Navpath>VARIOUS|VARIOUS|FRESHWATER FISHERIES PRODUCTION</Navpath>
    <Navpath>VARIOUS|VARIOUS|WATER USE</Navpath>
    <Navpath>VARIOUS|VARIOUS|LAND USE</Navpath>
    <Navpath>VARIOUS|VARIOUS|AGRICULTURAL PRODUCTION</Navpath>
    <Navpath>VARIOUS|VARIOUS|FERTILIZERS</Navpath>
    <Navpath>VARIOUS|VARIOUS|PESTICIDES</Navpath>
    <Navpath>VARIOUS|VARIOUS|TRADE</Navpath>
    <Navpath>VARIOUS|VARIOUS|ENERGY SUPPLY AND CONSUMPTION</Navpath>
    <Navpath>VARIOUS|VARIOUS|POPULATION</Navpath>
    <Navpath>VARIOUS|VARIOUS|TRANSPORTATION</Navpath>
    <Navpath>VARIOUS|VARIOUS|COMMUNICATIONS</Navpath>
    <Navpath>VARIOUS|VARIOUS|GROSS DOMESTIC PRODUCT</Navpath>
    <Navpath>VARIOUS|VARIOUS|VITAL STATISTICS</Navpath>
    <Navpath>VARIOUS|VARIOUS|ACCESS TO IMPROVED SANITATION AND WATER SUPPLY</Navpath>
    <Navpath>VARIOUS|VARIOUS|EDUCATIONAL ENROLLMENT/ATTAINMENT</Navpath>
    <Navpath>VARIOUS|VARIOUS|URBAN POPULATION</Navpath>
    <Principal_Investigator>
      <Name>van Woerden, Jaap</Name>
      <Email>Woerden@grid.unep.ch</Email>
    </Principal_Investigator>
    <Data_Set_Link>
      <URL>http://geodata.grid.unep.ch/</URL>
      <Label>Global Environmental Outlook (GEO) Data Portal</Label>
      <Link_Note>The GEO Data Portal offers users the option to: (1) draw, view and explore maps, graphs and tables online; (2) view documentation and other metadata; and/or (3) download data sets as Excel, PDF, CSV, XML or ARCINFO Shape files as appropriate.</Link_Note>
    </Data_Set_Link>
    <Documentation_Link>
      <URL>http://www.unep.org/GEO/index.htm</URL>
      <Label>Global Environmental Outlook (GEO) Home Page</Label>
      <Text />
    </Documentation_Link>
    <Documentation_Link>
      <URL>http://www.unep.org/GEO/geo3/</URL>
      <Label>GEO: Global Environment Outlook 3</Label>
      <Text />
    </Documentation_Link>
    <Documentation_Link>
      <URL>http://geocompendium.grid.unep.ch/</URL>
      <Label>GEO-3 Data Compendium</Label>
      <Text />
    </Documentation_Link>
    <Documentation_Link>
      <URL />
      <Label />
    </Documentation_Link>
    <Alternate_Data_Access>
      <Data_Set_Status />
      <Data_Set_Restrictions />
      <Data_Set_Location />
      <Data_Contact_Person>
        <Email />
        <Name />
        <Phone />
        <Data_Center_URL />
      </Data_Contact_Person>
      <Data_Center_URL />
      <Data_Set_Citation />
      <Data_Set_Link>
        <URL />
        <Label />
        <Link_Note />
        <Data_Center_URL />
      </Data_Set_Link>
    </Alternate_Data_Access>
    <OME_Software_Version>Version 4.7.5, Revision Date: 04 Apr 2006</OME_Software_Version>
    <OME_DTD_Version>metadata24.dtd</OME_DTD_Version>
    <Contact_Person>
      <Email>Woerden@grid.unep.ch</Email>
      <Name>van Woerden, Jaap</Name>
      <Phone>+41-22-917-8294</Phone>
    </Contact_Person>
    <Temporal_Resolution />
    <enddate_blank />
    <File_ID>Created 20021226 185437 by 206.246.119.93</File_ID>
    <Spatial_Reference_Method>Point</Spatial_Reference_Method>
    <Spatial_Reference_Method>Raster</Spatial_Reference_Method>
    <Spatial_Extent>64800</Spatial_Extent>
    <Search_Text_Link>
      <URL>http://www.unep.org/GEO/index.htm</URL>
      <Label>Global Environmental Outlook (GEO) Home Page</Label>
    </Search_Text_Link>
    <Search_Text_Link>
      <URL>http://www.unep.org/GEO/geo3/</URL>
      <Label>GEO: Global Environment Outlook 3</Label>
    </Search_Text_Link>
    <Search_Text_Link>
      <URL>http://geocompendium.grid.unep.ch/</URL>
      <Label>GEO-3 Data Compendium</Label>
    </Search_Text_Link>
    <Other_Link>
      <URL />
      <Label />
    </Other_Link>
    <Granule_Details />
    <OGC_URL />
  </mercury>
  <sourceData>database</sourceData>
</metadata>