<metadata xmlns:ns0="http://purl.org/ornl/schema/mercury/terms/v1.0" xmlns:xsi="http://www.w3.org/2001/XMLSchema-instance" xsi:schemaLocation="http://purl.org/ornl/schema/mercury/terms/v1.0 mercury-ornl-v1.xsd">
  <idinfo>
    <citation>
      <citeinfo>
        <origin>Brown, Sandra</origin>
        <origin>Iverson, Louis R.</origin>
        <origin>Prasad, Anantha</origin>
        <title>Geographical Distribution of Biomass Carbon in Tropical Southeast Asian Forests (NDP-068)</title>
        <onlink>http://daac.ornl.gov/metadata/bluangel_harvest/RGED/curtis/metadata/npp/biomass_carbon.xml</onlink>
        <alt_onlink>http://daac.ornl.gov/metadata/bluangel_harvest/RGED/curtis/metadata/npp/biomass_carbon.xml</alt_onlink>
        <onlink>http://cdiac.ornl.gov/epubs/ndp/ndp068/ndp068.html</onlink>
        <onlink>http://cdiac.ornl.gov/ftp/ndp068/ndp068.txt</onlink>
        <onlink>http://cdiac.ornl.gov/epubs/ndp/ndp068/ndp068t3.html</onlink>
        <onlink>http://cdiac.ornl.gov/epubs/ndp/ndp068/geocarto.pdf</onlink>
      </citeinfo>
    </citation>
    <descript>
      <abstract>A database (NDP-068) was generated from estimates of geographically referenced carbon densities of forest vegetation in tropical Southeast Asia for 1980. A geographic information system (GIS) was used to incorporate spatial databases of climatic, edaphic, and geomorphological indices and vegetation to estimate potential (i.e., in the absence of human intervention and natural disturbance) carbon densities of forests. The resulting map was then modified to estimate actual 1980 carbon density as a function of population density and climatic zone. The database covers the following 13 countries: Bangladesh, Brunei, Cambodia (Campuchea), India, Indonesia, Laos, Malaysia, Myanmar (Burma), Nepal, the Philippines, Sri Lanka, Thailand, and Vietnam. 

The data sets within this database are provided in three file formats: ARC/INFOTM exported integer grids; ASCII (American Standard Code for Information  Interchange) files formatted for raster-based GIS software packages; and generic ASCII files with x, y coordinates for use with non-GIS software packages. 

The database includes ten ARC/INFO exported integer grid files (five with the pixel size 3.75 km x 3.75 km and five with the pixel size 0.25 degree longitude x 0.25 degree latitude) and 27 ASCII files. The first ASCII file contains the documentation associated with this database. Twenty-four of the ASCII files were generated by means of the ARC/INFO GRIDASCII command and can be used by most raster-based GIS software packages. The 24 files can be subdivided into two groups of 12 files each. 

The files contain real data values representing actual carbon and potential carbon density in Mg C/ha (1 megagram = 10^6 grams) and integer-coded values for country name, Weck's Climatic Index, ecofloristic zone, elevation, forest or non- forest designation, population density, mean annual precipitation, slope, soil texture, and vegetation classification. One set of 12 files contains these data at a spatial resolution of 3.75 km, whereas the other set of 12 files has a spatial resolution of 0.25 degree. The remaining two ASCII data files combine all of the data from the 24 ASCII data files into 2 single generic data files. The first file has a spatial resolution of 3.75 km, and the second has a resolution of 0.25 degree. Both files also provide a grid-cell identification number and the longitude and latitude of the centerpoint of each grid cell. 

The 3.75-km data in this numeric data package yield an actual total carbon estimate of 42.1 Pg (1 petagram = 10^15 grams) and a potential carbon estimate of 73.6 Pg; whereas the 0.25-degree data produced an actual total carbon estimate of 41.8 Pg and a total potential carbon estimate of 73.9 Pg. 

Fortran and SASTM access codes are provided to read the ASCII data files, and ARC/INFO and ARCVIEW command syntax are provided to import the ARC/INFO exported integer grid files. The data files and this documentation are available without charge on a variety of media and via the Internet from the Carbon Dioxide Information Analysis Center (CDIAC).</abstract>
      <supplinf />
    </descript>
    <timeperd>
      <timeinfo>
        <rngdates>
          <begdate>19800101</begdate>
          <enddate>19801231</enddate>
        </rngdates>
      </timeinfo>
    </timeperd>
    <status>
      <progress>Final</progress>
      <update>As appropriate</update>
    </status>
    <spdom>
      <bounding>
        <westbc>44.25875</westbc>
        <eastbc>149.50875</eastbc>
        <northbc>42.97046</northbc>
        <southbc>-16.52954</southbc>
      </bounding>
    </spdom>
    <keywords>
      <theme>
        <themekt>Parameter_Sensor_Source</themekt>
        <themekey>BIOMASS|GIS MODELING APPROACH|SPATIAL DATABASES</themekey>
        <themekey>CARBON|GIS MODELING APPROACH|SPATIAL DATABASES</themekey>
      </theme>
      <theme>
        <themekt>Parameter</themekt>
        <themekey>BIOMASS</themekey>
      </theme>
      <theme>
        <themekt>Source</themekt>
        <themekey>SPATIAL DATABASES</themekey>
      </theme>
      <theme>
        <themekt>Sensor</themekt>
        <themekey>GIS MODELING APPROACH</themekey>
      </theme>
      <place>
        <placekt>Place Keywords</placekt>
        <placekey>Southeast Asia</placekey>
      </place>
    </keywords>
    <ptcontac>
      <cntinfo>
        <cntperp>
          <cntper>Brown, Sandra</cntper>
        </cntperp>
        <cntfax>6.1.10.8 Contact Electronic Mail: INTERNET &amp;gt; sbrown@winrock.org</cntfax>
      </cntinfo>
    </ptcontac>
  </idinfo>
  <distinfo>
    <distrib>
      <cntinfo>
        <cntperp>
          <cntorg>Carbon Dioxide Information Analysis Center, U.S. Department of Energy, Oak Ridge National Laboratory, Oak Ridge, Tennessee, USA</cntorg>
          <cntper>Boden, Thomas A.</cntper>
        </cntperp>
        <cntvoice>+1-865-241-4842 (Phone)  +1-865-574-2232 (Fax)</cntvoice>
        <cntfax>6.1.10.8 Contact Electronic Mail: INTERNET &amp;gt; sbrown@winrock.org</cntfax>
        <cntemail>bodenta@ornl.gov</cntemail>
      </cntinfo>
    </distrib>
    <stdorder>
      <digform>
        <digtopt>
          <onlinopt>
            <computer>http://cdiac.ornl.gov/</computer>
            <accinstr>Public</accinstr>
          </onlinopt>
        </digtopt>
      </digform>
    </stdorder>
    <resdesc>Brown, S., L.R. Iverson, and A. Prasad. 2001. Geographical Distribution of Biomass Carbon in Tropical Southeast Asian Forests: A Database. ORNL/CDIAC-119, NDP-068. Available at [http://cdiac.ornl.gov/epubs/ndp/ndp068/ndp068.html] from the Carbon Dioxide Information Analysis Center, U.S. Department of Energy, Oak Ridge National Laboratory, Oak Ridge, Tennessee, USA.</resdesc>
  </distinfo>
  <metainfo>
    <metd>20081117 043440</metd>
    <metc>
      <cntinfo>
        <cntorgp>
          <cntper>Curtis, Carroll</cntper>
        </cntorgp>
        <cntperp>
          <cntper>Curtis, Carroll</cntper>
        </cntperp>
        <cntvoice>+1-804-769-2495</cntvoice>
        <cntemail>cncurtis@crosslink.net</cntemail>
      </cntinfo>
    </metc>
    <metstdn>FGDC Content Standard for Digital Geospatial Metadata</metstdn>
  </metainfo>
  <mercury>
    <begdate>19800101</begdate>
    <enddate>19801231</enddate>
    <Site_Information>
      <Site>Southeast Asia</Site>
      <Westernmost_Longitude>44.25875</Westernmost_Longitude>
      <Easternmost_Longitude>149.50875</Easternmost_Longitude>
      <Northernmost_Latitude>42.97046</Northernmost_Latitude>
      <Southernmost_Latitude>-16.52954</Southernmost_Latitude>
    </Site_Information>
    <Keywords>Biomass</Keywords>
    <Keywords>Carbon</Keywords>
    <Keywords>Carbon cycle</Keywords>
    <Keywords>CDIAC</Keywords>
    <Keywords>Climate</Keywords>
    <Keywords>Elevation</Keywords>
    <Keywords>EOSDIS</Keywords>
    <Keywords>Forests</Keywords>
    <Keywords>Land use</Keywords>
    <Keywords>Organic matter</Keywords>
    <Keywords>Population</Keywords>
    <Keywords>Slope</Keywords>
    <Keywords>Soils</Keywords>
    <Keywords>Southeast Asia</Keywords>
    <Keywords>Tropics</Keywords>
    <Keywords>Vegetation</Keywords>
    <Keywords>Vegetation Collections</Keywords>
    <Parameter_Description>
      <Parameter>BIOMASS</Parameter>
      <Sensor>GIS MODELING APPROACH</Sensor>
      <Source>SPATIAL DATABASES</Source>
      <Term>VEGETATION</Term>
      <Topic>BIOSPHERE</Topic>
    </Parameter_Description>
    <Parameter_Description>
      <Parameter>CARBON</Parameter>
      <Sensor>GIS MODELING APPROACH</Sensor>
      <Source>SPATIAL DATABASES</Source>
      <Term>VEGETATION</Term>
      <Topic>BIOSPHERE</Topic>
    </Parameter_Description>
    <Project />
    <Navpath>SPATIAL DATABASES|GIS MODELING APPROACH|BIOMASS</Navpath>
    <Navpath>SPATIAL DATABASES|GIS MODELING APPROACH|CARBON</Navpath>
    <Principal_Investigator>
      <Name>Brown, Sandra</Name>
      <Email>sbrown@winrock.org</Email>
    </Principal_Investigator>
    <Principal_Investigator>
      <Name>Iverson, Louis R.</Name>
      <Email>liverson@fs.fed.us</Email>
    </Principal_Investigator>
    <Principal_Investigator>
      <Name>Prasad, Anantha</Name>
      <Email>aprasad@fs.fed.us</Email>
    </Principal_Investigator>
    <Data_Set_Link>
      <URL>http://cdiac.ornl.gov/ftp/ndp068/</URL>
      <Label>Geographical Distribution of Biomass Carbon in Tropical Southeast Asian Forests: A Database (NDP-068)</Label>
      <Link_Note>You can download the data sets within this database as well as ASCII documentation files from this CDIAC FTP area.</Link_Note>
    </Data_Set_Link>
    <Documentation_Link>
      <URL>http://cdiac.ornl.gov/epubs/ndp/ndp068/ndp068.html</URL>
      <Label>Geographical Distribution of Biomass Carbon in Tropical Southeast Asian Forests: A Database (NDP-068) Web Page</Label>
      <Text />
    </Documentation_Link>
    <Documentation_Link>
      <URL>http://cdiac.ornl.gov/ftp/ndp068/ndp068.txt</URL>
      <Label>Documentation File for NDP-068 (txt format)</Label>
      <Text />
    </Documentation_Link>
    <Documentation_Link>
      <URL>http://cdiac.ornl.gov/epubs/ndp/ndp068/ndp068t3.html</URL>
      <Label>List Of Files in NDP-068</Label>
      <Text />
    </Documentation_Link>
    <Documentation_Link>
      <URL>http://cdiac.ornl.gov/epubs/ndp/ndp068/geocarto.pdf</URL>
      <Label>Description of Methods and Data Sources for NDP-068 (PDF reprint of Brown et al. paper in Geocarto International, Vol. 8; copyright 1993 Geocarto International Centre and reprinted with kind permission from the publisher)</Label>
    </Documentation_Link>
    <Alternate_Data_Access>
      <Data_Set_Status />
      <Data_Set_Restrictions />
      <Data_Set_Location />
      <Data_Contact_Person>
        <Email />
        <Name />
        <Phone />
        <Data_Center_URL />
      </Data_Contact_Person>
      <Data_Center_URL />
      <Data_Set_Citation />
      <Data_Set_Link>
        <URL />
        <Label />
        <Link_Note />
        <Data_Center_URL />
      </Data_Set_Link>
    </Alternate_Data_Access>
    <OME_Software_Version>Version 4.7.5, Revision Date: 04 Apr 2006</OME_Software_Version>
    <OME_DTD_Version>metadata24.dtd</OME_DTD_Version>
    <Contact_Person>
      <Email>bodenta@ornl.gov</Email>
      <Name>Boden, Thomas A.</Name>
      <Phone>+1-865-241-4842 (Phone)  +1-865-574-2232 (Fax)</Phone>
    </Contact_Person>
    <Temporal_Resolution />
    <enddate_blank />
    <File_ID>Created 20010620 135028 by 206.246.119.88</File_ID>
    <Spatial_Reference_Method>Raster</Spatial_Reference_Method>
    <Spatial_Extent>6262.375</Spatial_Extent>
    <Search_Text_Link>
      <URL>http://cdiac.ornl.gov/epubs/ndp/ndp068/ndp068.html</URL>
      <Label>Geographical Distribution of Biomass Carbon in Tropical Southeast Asian Forests: A Database (NDP-068) Web Page</Label>
    </Search_Text_Link>
    <Search_Text_Link>
      <URL>http://cdiac.ornl.gov/ftp/ndp068/ndp068.txt</URL>
      <Label>Documentation File for NDP-068 (txt format)</Label>
    </Search_Text_Link>
    <Search_Text_Link>
      <URL>http://cdiac.ornl.gov/epubs/ndp/ndp068/ndp068t3.html</URL>
      <Label>List Of Files in NDP-068</Label>
    </Search_Text_Link>
    <Other_Link>
      <URL>http://cdiac.ornl.gov/epubs/ndp/ndp068/geocarto.pdf</URL>
      <Label>Description of Methods and Data Sources for NDP-068 (PDF reprint of Brown et al. paper in Geocarto International, Vol. 8; copyright 1993 Geocarto International Centre and reprinted with kind permission from the publisher)</Label>
    </Other_Link>
    <Granule_Details />
    <OGC_URL />
  </mercury>
  <sourceData>database</sourceData>
</metadata>