<ns0:systemMetadata xmlns:ns0="http://ns.dataone.org/service/types/v1"><serialVersion>1</serialVersion><identifier>http://dx.doi.org/10.5061/dryad.sd080/12?ver=2013-01-30T12:24:51.972-05:00</identifier><formatId>http://datadryad.org/profile/v3.1</formatId><size>4121</size><checksum algorithm="MD5">6583a25cfd194d45d3deee0e126e7228</checksum><submitter>brant.faircloth@gmail.com</submitter><rightsHolder>admin@datadryad.org</rightsHolder><accessPolicy><allow><subject>public</subject><permission>read</permission></allow></accessPolicy><replicationPolicy replicationAllowed="false" /><archived>false</archived><dateUploaded>2013-01-30T17:24:51.000+00:00</dateUploaded><dateSysMetadataModified>2014-02-22T09:37:59.568+00:00</dateSysMetadataModified><originMemberNode>urn:node:DRYAD</originMemberNode><authoritativeMemberNode>urn:node:DRYAD</authoritativeMemberNode><replica><replicaMemberNode>urn:node:DRYAD</replicaMemberNode><replicationStatus>completed</replicationStatus><replicaVerified>2014-02-22T09:37:58.892+00:00</replicaVerified></replica><replica><replicaMemberNode>urn:node:CN</replicaMemberNode><replicationStatus>completed</replicationStatus><replicaVerified>2014-02-22T09:37:58.969+00:00</replicaVerified></replica></ns0:systemMetadata>