<ns0:systemMetadata xmlns:ns0="http://ns.dataone.org/service/types/v1"><serialVersion>12</serialVersion><identifier>doi:10.5063/AA/Pitt.22.7</identifier><formatId>eml://ecoinformatics.org/eml-2.1.0</formatId><size>35349</size><checksum algorithm="MD5">e7c95967d4e7b4051ba0d435a657b6f2</checksum><submitter>uid=Kelly Robinson,o=unaffiliated,dc=ecoinformatics,dc=org</submitter><rightsHolder>uid=Pitt,o=unaffiliated,dc=ecoinformatics,dc=org</rightsHolder><accessPolicy><allow><subject>uid=Cathy Lucas,o=unaffiliated,dc=ecoinformatics,dc=org</subject><permission>read</permission><permission>write</permission></allow><allow><subject>uid=haddock,o=unaffiliated,dc=ecoinformatics,dc=org</subject><permission>read</permission><permission>write</permission></allow><allow><subject>uid=condon,o=unaffiliated,dc=ecoinformatics,dc=org</subject><permission>read</permission><permission>write</permission><permission>changePermission</permission></allow><allow><subject>uid=regetz,o=NCEAS,dc=ecoinformatics,dc=org</subject><permission>read</permission><permission>write</permission><permission>changePermission</permission></allow><allow><subject>public</subject><permission>read</permission></allow><allow><subject>uid=mgraham,o=unaffiliated,dc=ecoinformatics,dc=org</subject><permission>read</permission><permission>write</permission><permission>changePermission</permission></allow><allow><subject>uid=Pitt,o=unaffiliated,dc=ecoinformatics,dc=org</subject><permission>read</permission><permission>write</permission></allow><allow><subject>uid=schild,o=NCEAS,dc=ecoinformatics,dc=org</subject><permission>read</permission><permission>write</permission><permission>changePermission</permission></allow><allow><subject>uid=malej,o=unaffiliated,dc=ecoinformatics,dc=org</subject><permission>read</permission><permission>write</permission></allow><allow><subject>uid=aaronelmore,o=unaffiliated,dc=ecoinformatics,dc=org</subject><permission>read</permission><permission>write</permission><permission>changePermission</permission></allow><allow><subject>uid=lhu,o=unaffiliated,dc=ecoinformatics,dc=org</subject><permission>read</permission><permission>write</permission><permission>changePermission</permission></allow><allow><subject>uid=Kelly Robinson,o=unaffiliated,dc=ecoinformatics,dc=org</subject><permission>read</permission><permission>write</permission><permission>changePermission</permission></allow></accessPolicy><replicationPolicy numberReplicas="2" replicationAllowed="true"><preferredMemberNode /><blockedMemberNode /></replicationPolicy><obsoletes>doi:10.5063/AA/Pitt.22.6</obsoletes><archived>false</archived><dateUploaded>2010-08-03T23:00:00.000+00:00</dateUploaded><dateSysMetadataModified>2014-12-14T04:28:36.023+00:00</dateSysMetadataModified><originMemberNode>urn:node:KNB</originMemberNode><authoritativeMemberNode>urn:node:KNB</authoritativeMemberNode><replica><replicaMemberNode>urn:node:CN</replicaMemberNode><replicationStatus>completed</replicationStatus><replicaVerified>2014-09-12T19:09:15.064+00:00</replicaVerified></replica><replica><replicaMemberNode>urn:node:mnUNM1</replicaMemberNode><replicationStatus>completed</replicationStatus><replicaVerified>2014-12-14T04:28:20.345+00:00</replicaVerified></replica><replica><replicaMemberNode>urn:node:mnORC1</replicaMemberNode><replicationStatus>completed</replicationStatus><replicaVerified>2014-12-14T04:28:28.396+00:00</replicaVerified></replica><replica><replicaMemberNode>urn:node:KNB</replicaMemberNode><replicationStatus>completed</replicationStatus><replicaVerified>2014-12-14T04:28:35.240+00:00</replicaVerified></replica></ns0:systemMetadata>