<ns0:systemMetadata xmlns:ns0="http://ns.dataone.org/service/types/v1"><serialVersion>1</serialVersion><identifier>doi_10.5066_F7R78C5P</identifier><formatId>FGDC-STD-001-1998</formatId><size>28537</size><checksum algorithm="MD5">e71d08e59a246fa8c81617939620d300</checksum><submitter>csas (CN=csas,DC=cilogon,DC=org)</submitter><rightsHolder>csas (CN=csas,DC=cilogon,DC=org)</rightsHolder><accessPolicy><allow><subject>public</subject><permission>read</permission></allow></accessPolicy><replicationPolicy replicationAllowed="false" /><archived>false</archived><dateUploaded>2013-04-27T12:00:55.000+00:00</dateUploaded><dateSysMetadataModified>2013-06-25T15:42:17.481+00:00</dateSysMetadataModified><originMemberNode>urn:node:USGSCSAS</originMemberNode><authoritativeMemberNode>urn:node:USGSCSAS</authoritativeMemberNode><replica><replicaMemberNode>urn:node:CN</replicaMemberNode><replicationStatus>completed</replicationStatus><replicaVerified>2013-06-25T15:42:16.117+00:00</replicaVerified></replica><replica><replicaMemberNode>urn:node:USGSCSAS</replicaMemberNode><replicationStatus>completed</replicationStatus><replicaVerified>2013-06-25T15:42:15.936+00:00</replicaVerified></replica></ns0:systemMetadata>