<ns0:systemMetadata xmlns:ns0="http://ns.dataone.org/service/types/v1"><serialVersion>10</serialVersion><identifier>dcx_148eeac1-59d6-4e13-9130-fbe1c2a0b66c_0</identifier><formatId>http://ns.dataone.org/metadata/schema/onedcx/v1.0</formatId><size>8473</size><checksum algorithm="SHA-1">e76f2a2437d4e088efec4805e9a382071cbaeabb</checksum><submitter>CN=jlong,O=International Arctic Research Center,ST=AK,C=US</submitter><rightsHolder>CN=jlong,O=International Arctic Research Center,ST=AK,C=US</rightsHolder><accessPolicy><allow><subject>public</subject><permission>read</permission></allow></accessPolicy><replicationPolicy numberReplicas="3" replicationAllowed="true" /><archived>false</archived><dateUploaded>2015-05-08T02:01:20.614+00:00</dateUploaded><dateSysMetadataModified>2015-05-08T23:30:06.499+00:00</dateSysMetadataModified><originMemberNode>urn:node:IARC</originMemberNode><authoritativeMemberNode>urn:node:IARC</authoritativeMemberNode><replica><replicaMemberNode>urn:node:IARC</replicaMemberNode><replicationStatus>completed</replicationStatus><replicaVerified>2015-05-08T21:47:41.228+00:00</replicaVerified></replica><replica><replicaMemberNode>urn:node:CN</replicaMemberNode><replicationStatus>completed</replicationStatus><replicaVerified>2015-05-08T21:47:41.293+00:00</replicaVerified></replica><replica><replicaMemberNode>urn:node:KNB</replicaMemberNode><replicationStatus>completed</replicationStatus><replicaVerified>2015-05-08T23:28:45.183+00:00</replicaVerified></replica><replica><replicaMemberNode>urn:node:mnUCSB1</replicaMemberNode><replicationStatus>completed</replicationStatus><replicaVerified>2015-05-08T23:28:49.103+00:00</replicaVerified></replica><replica><replicaMemberNode>urn:node:US_MPC</replicaMemberNode><replicationStatus>completed</replicationStatus><replicaVerified>2015-05-08T23:28:50.549+00:00</replicaVerified></replica></ns0:systemMetadata>