<ns0:systemMetadata xmlns:ns0="http://ns.dataone.org/service/types/v1"><serialVersion>1</serialVersion><identifier>peggym.1224.35</identifier><formatId>eml://ecoinformatics.org/eml-2.1.0</formatId><size>24828</size><checksum algorithm="MD5">37e29dfde2c2dc4c901f198c9a286594</checksum><submitter>uid=peggym,o=SANParks,dc=ecoinformatics,dc=org</submitter><rightsHolder>uid=peggym,o=SANParks,dc=ecoinformatics,dc=org</rightsHolder><accessPolicy><allow><subject>uid=peggym,o=SANParks,dc=ecoinformatics,dc=org</subject><permission>read</permission><permission>write</permission><permission>changePermission</permission></allow><allow><subject>public</subject><permission>read</permission></allow></accessPolicy><replicationPolicy replicationAllowed="false" /><obsoletes>peggym.1224.34</obsoletes><archived>false</archived><dateUploaded>2012-04-10T00:00:00.000+00:00</dateUploaded><dateSysMetadataModified>2013-02-01T06:21:33.378+00:00</dateSysMetadataModified><originMemberNode>urn:node:SANPARKS</originMemberNode><authoritativeMemberNode>urn:node:SANPARKS</authoritativeMemberNode><replica><replicaMemberNode>urn:node:SANPARKS</replicaMemberNode><replicationStatus>completed</replicationStatus><replicaVerified>2013-02-01T00:00:00.000+00:00</replicaVerified></replica><replica><replicaMemberNode>urn:node:CN</replicaMemberNode><replicationStatus>completed</replicationStatus><replicaVerified>2013-02-01T00:00:00.000+00:00</replicaVerified></replica></ns0:systemMetadata>